Workbook
Name Etapas: Listas!$A$1:$A$9
Name Motivos: Listas!$D$1:$D$6
Name Origens: Listas!$B$1:$B$8
Name Preferencias: Listas!$C$1:$C$3

Sheet Comece aqui
B2: Seu CRM de vendas para clínicas
B4: Registre os contatos na aba CRM. A aba Resumo acompanha o funil e os próximos retornos. Os exemplos fictícios ficam separados e não entram nos indicadores.
B7: 1 · Cadastre a clínica
B8: Preencha clínica, cidade, responsável e o canal comercial divulgado. Escreva uma observação concreta sobre o negócio.
B11: 2 · Atualize a etapa
B12: Use a lista da coluna Etapa conforme a conversa avança. Registre cada contato e o próximo passo.
B15: 3 · Agende o retorno
B16: Informe Próximo contato e Próxima ação. Situação do retorno sinaliza atrasos e contatos previstos para hoje.
B19: 4 · Respeite a preferência
B20: Selecione Não contatar quando houver recusa. Isso prevalece sobre o alerta de retorno. A planilha não envia mensagens.
B23: 5 · Registre a proposta
B24: Informe implantação e mensalidade em suas colunas. Ao fechar, marque Fechado e preencha Data do fechamento.
... B35: Referência comercial discutida: implantação de R$ 3.490 e manutenção de R$ 397/mês. São sugestões iniciais: ajuste ao escopo, aos custos e ao suporte oferecido. Custos externos e serviços ainda não implementados devem ser definidos separadamente.

Sheet CRM
A1: CRM · Prospecção e acompanhamento
A2: Preencha as células em azul. Use os filtros para selecionar etapa, origem e retornos pendentes. Não substitua as fórmulas da última coluna.
A4: Clínica | B4: Cidade / UF | C4: Responsável | D4: WhatsApp comercial | E4: E-mail comercial | F4: Instagram / site | G4: Origem | H4: Etapa | I4: Interesse / necessidade | J4: Último contato | K4: Próximo contato | L4: Próxima ação | M4: Preferência de contato | N4: Implantação proposta (R$) | O4: Mensalidade proposta (R$) | P4: Data do fechamento | Q4: Motivo da perda | R4: Observações | S4: Situação do retorno
S5: =IF(A5="","",IF(M5="Não contatar","Não contatar",IF(OR(H5="Fechado",H5="Perdido"),"Encerrado",IF(K5="","Sem data",IF(K5<TODAY(),"Atrasado",IF(K5=TODAY(),"Hoje","Agendado")))))))
S6: =IF(A6="","",IF(M6="Não contatar","Não contatar",IF(OR(H6="Fechado",H6="Perdido"),"Encerrado",IF(K6="","Sem data",IF(K6<TODAY(),"Atrasado",IF(K6=TODAY(),"Hoje","Agendado")))))))
S7: =IF(A7="","",IF(M7="Não contatar","Não contatar",IF(OR(H7="Fechado",H7="Perdido"),"Encerrado",IF(K7="","Sem data",IF(K7<TODAY(),"Atrasado",IF(K7=TODAY(),"Hoje","Agendado")))))))
S8: =IF(A8="","",IF(M8="Não contatar","Não contatar",IF(OR(H8="Fechado",H8="Perdido"),"Encerrado",IF(K8="","Sem data",IF(K8<TODAY(),"Atrasado",IF(K8=TODAY(),"Hoje","Agendado")))))))
S9: =IF(A9="","",IF(M9="Não contatar","Não contatar",IF(OR(H9="Fechado",H9="Perdido"),"Encerrado",IF(K9="","Sem data",IF(K9<TODAY(),"Atrasado",IF(K9=TODAY(),"Hoje","Agendado")))))))
S10: =IF(A10="","",IF(M10="Não contatar","Não contatar",IF(OR(H10="Fechado",H10="Perdido"),"Encerrado",IF(K10="","Sem data",IF(K10<TODAY(),"Atrasado",IF(K10=TODAY(),"Hoje","Agendado")))))))
S11: =IF(A11="","",IF(M11="Não contatar","Não contatar",IF(OR(H11="Fechado",H11="Perdido"),"Encerrado",IF(K11="","Sem data",IF(K11<TODAY(),"Atrasado",IF(K11=TODAY(),"Hoje","Agendado")))))))
S12: =IF(A12="","",IF(M12="Não contatar","Não contatar",IF(OR(H12="Fechado",H12="Perdido"),"Encerrado",IF(K12="","Sem data",IF(K12<TODAY(),"Atrasado",IF(K12=TODAY(),"Hoje","Agendado")))))))
S13: =IF(A13="","",IF(M13="Não contatar","Não contatar",IF(OR(H13="Fechado",H13="Perdido"),"Encerrado",IF(K13="","Sem data",IF(K13<TODAY(),"Atrasado",IF(K13=TODAY(),"Hoje","Agendado")))))))
S14: =IF(A14="","",IF(M14="Não contatar","Não contatar",IF(OR(H14="Fechado",H14="Perdido"),"Encerrado",IF(K14="","Sem data",IF(K14<TODAY(),"Atrasado",IF(K14=TODAY(),"Hoje","Agendado")))))))
S15: =IF(A15="","",IF(M15="Não contatar","Não contatar",IF(OR(H15="Fechado",H15="Perdido"),"Encerrado",IF(K15="","Sem data",IF(K15<TODAY(),"Atrasado",IF(K15=TODAY(),"Hoje","Agendado")))))))
S16: =IF(A16="","",IF(M16="Não contatar","Não contatar",IF(OR(H16="Fechado",H16="Perdido"),"Encerrado",IF(K16="","Sem data",IF(K16<TODAY(),"Atrasado",IF(K16=TODAY(),"Hoje","Agendado")))))))
... S204: =IF(A204="","",IF(M204="Não contatar","Não contatar",IF(OR(H204="Fechado",H204="Perdido"),"Encerrado",IF(K204="","Sem data",IF(K204<TODAY(),"Atrasado",IF(K204=TODAY(),"Hoje","Agendado")))))))

Sheet Listas
A1: Prospectar | B1: Google Maps | C1: A confirmar | D1: Sem interesse
A2: Contatado | B2: Instagram | C2: Autorizado | D2: Sem orçamento
A3: Em conversa | B3: Indicação | C3: Não contatar | D3: Já tem solução
A4: Demonstração marcada | B4: WhatsApp | D4: Sem retorno
A5: Proposta enviada | B5: E-mail | D5: Sem prioridade
A6: Negociação | B6: Anúncio | D6: Outro
A7: Fechado | B7: Evento
A8: Perdido | B8: Outro
A9: Retomar depois

Sheet Resumo
B2: Resumo comercial
B5: Indicadores calculados a partir das clínicas preenchidas na aba CRM.
B7: Clínicas cadastradas | F7: Retornos atrasados | J7: Retornos para hoje
B8: =COUNTA(CRM!A5:A204) -> 0 | F8: =COUNTIF(CRM!S5:S204,"Atrasado") -> 0 | J8: =COUNTIF(CRM!S5:S204,"Hoje") -> 0
B11: Contratos fechados | F11: Implantação fechada | J11: Mensalidade contratada
B12: =COUNTIFS(CRM!A5:A204,"<>",CRM!H5:H204,"Fechado") -> 0 | F12: =SUMIFS(CRM!N5:N204,CRM!A5:A204,"<>",CRM!H5:H204,"Fechado") -> 0 | J12: =SUMIFS(CRM!O5:O204,CRM!A5:A204,"<>",CRM!H5:H204,"Fechado") -> 0
B16: Funil por etapa
B17: Etapa | E17: Clínicas
B18: Prospectar | E18: =COUNTIFS(CRM!A5:A204,"<>",CRM!H5:H204,B18) -> 0
B19: Contatado | E19: =COUNTIFS(CRM!A5:A204,"<>",CRM!H5:H204,B19) -> 0
B20: Em conversa | E20: =COUNTIFS(CRM!A5:A204,"<>",CRM!H5:H204,B20) -> 0
B21: Demonstração marcada | E21: =COUNTIFS(CRM!A5:A204,"<>",CRM!H5:H204,B21) -> 0
B22: Proposta enviada | E22: =COUNTIFS(CRM!A5:A204,"<>",CRM!H5:H204,B22) -> 0
B23: Negociação | E23: =COUNTIFS(CRM!A5:A204,"<>",CRM!H5:H204,B23) -> 0
B24: Fechado | E24: =COUNTIFS(CRM!A5:A204,"<>",CRM!H5:H204,B24) -> 0
B25: Perdido | E25: =COUNTIFS(CRM!A5:A204,"<>",CRM!H5:H204,B25) -> 0
B26: Retomar depois | E26: =COUNTIFS(CRM!A5:A204,"<>",CRM!H5:H204,B26) -> 0
B29: Pipeline de propostas (implantação)
B30: =SUMIFS(CRM!N5:N204,CRM!A5:A204,"<>",CRM!H5:H204,"Proposta enviada")+SUMIFS(CRM!N5:N204,CRM!A5:A204,"<>",CRM!H5:H204,"Negociação") -> 0
B33: Mensalidade contratada é a soma das propostas marcadas como Fechado; não representa pagamentos recebidos. O pipeline considera implantação das propostas em negociação, sem estimar probabilidade de fechamento. Registre cobranças e recebimentos em um controle financeiro separado.

Sheet Exemplo fictício
A1: Exemplos fictícios · não entram no Resumo
A2: Use estas três linhas como referência de preenchimento. Não são contatos reais. Cadastre suas clínicas somente na aba CRM.
A4: Clínica | B4: Cidade / UF | C4: Responsável | D4: WhatsApp comercial | E4: E-mail comercial | F4: Instagram / site | G4: Origem | H4: Etapa | I4: Interesse / necessidade | J4: Último contato | K4: Próximo contato | L4: Próxima ação | M4: Preferência de contato | N4: Implantação proposta (R$) | O4: Mensalidade proposta (R$) | P4: Data do fechamento | Q4: Motivo da perda | R4: Observações | S4: Situação do retorno
A5: Clínica Aurora · exemplo | B5: São Paulo / SP | C5: Responsável fictício | G5: Instagram | H5: Demonstração marcada | I5: Quer organizar os pedidos do WhatsApp | J5: 46302 | K5: 46303 | L5: Apresentar o fluxo de solicitação e aprovação | M5: Autorizado | N5: 3490 | O5: 397 | R5: Demonstração de 15 minutos | S5: Agendado
A6: Clínica Horizonte · exemplo | B6: Campinas / SP | C6: Responsável fictício | G6: Indicação | H6: Proposta enviada | I6: Precisa atualizar tratamentos e fotos | J6: 46300 | K6: 46302 | L6: Verificar dúvidas sobre a proposta | M6: Autorizado | N6: 3490 | O6: 397 | R6: Combinar prazo após receber o material | S6: Hoje
A7: Clínica Jardim · exemplo | B7: Curitiba / PR | C7: Responsável fictício | G7: Google Maps | H7: Perdido | I7: Sem prioridade neste momento | J7: 46302 | L7: Encerrar os retornos | M7: Não contatar | Q7: Sem prioridade | R7: Respeitar a preferência registrada | S7: Não contatar
