Workbook
Name Etapas: 'Listas'!$A$1:$A$9

Sheet Listas
A1: Prospectar
A2: Contatado
A3: Em conversa
A4: Demonstração marcada
A5: Proposta enviada
A6: Negociação
A7: Fechado
A8: Perdido
A9: Retomar depois

Sheet CRM
A1: CRM de clínicas • CRM
A2: Pesquisa em 07/10/2026. Notas estimadas por evidências públicas; sem contato enviado. Edite sua cópia na aba CRM. Abas Qualificados/Pendentes são retratos da pesquisa.
A4: Clínica | B4: Cidade/UF | C4: Responsável | D4: WhatsApp comercial | E4: E-mail comercial | F4: Instagram/site | G4: Origem | H4: Etapa | I4: Interesse/necessidade | J4: Último contato | K4: Próximo contato | L4: Próxima ação | M4: Preferência de contato | N4: Implantação proposta R$ | O4: Mensalidade proposta R$ | P4: Data fechamento | Q4: Motivo perda | R4: Observações | S4: Situação retorno | T4: Canal principal | U4: Contato principal | V4: Site verificado | W4: Fonte pública contato | X4: Data verificação | Y4: Verificação | Z4: Potencial 0–10 | AA4: Capacidade estimada 0–10 | AB4: Evidências potencial | AC4: Evidências capacidade | AD4: Prioridade | AE4: País clínica | AF4: Proprietário identificado | AG4: Proprietário brasileiro? | AH4: Fonte proprietário/origem | AI4: Localização | AJ4: Confiança da capacidade | AK4: Qualificação | AL4: Pendência
A5: Instituto Remodele | B5: São Paulo/SP | C5: Não identificado | D5: +55 11 91907-8160 | E5: contato@remodele.com.br | F5: https://remodele.com.br/ | G5: Pesquisa pública | H5: Prospectar | I5: Chamadas de agendamento levam ao WhatsApp; catálogo facial e corporal permite apresentar site com solicitações de consulta e painel. | L5: Confirmar proprietário brasileiro; apresentar fluxo de agendamento e edição dos serviços. | M5: A confirmar | R5: CNPJ 63.154.444/0001-00; contato@remodele.com.br. Não confundir com Instituto Remodele de Rio Preto. | S5: =IF(A5="","",IF(H5="Fechado","Fechado",IF(H5="Perdido","Perdido",IF(K5="","Sem data",IF(K5<TODAY(),"Atrasado",IF(K5=TODAY(),"Hoje","Agendado"))))))) -> Sem data | T5: WhatsApp | U5: +55 11 91907-8160 | V5: https://remodele.com.br/ | W5: https://remodele.com.br/assets/index-ClmuxGc9.js | X5: 46302 | Y5: Verificado | Z5: 8 | AA5: 5 | AB5: Chamadas de agendamento levam ao WhatsApp; catálogo facial e corporal permite apresentar site com solicitações de consulta e painel. | AC5: Site próprio e endereço físico publicados; equipe, unidades adicionais e investimento disponíveis não comprovados. | AD5: =IF(A5="","",IF(OR(AK5<>"Qualificado",Y5<>"Verificado",U5="",Z5="",AA5=""),"Pendente",IF(AND(Z5>=7,AA5>=6),"Alta",IF(AND(Z5>=5,AA5>=4),"Média","Baixa")))) -> Pendente | AE5: Brasil | AF5: Não identificado | AG5: Não confirmado | AI5: Brasil | AJ5: Média | AK5: Pendente | AL5: Confirmar proprietário/origem brasileira
A6: Art Beauty Center | B6: São Paulo/SP; Uberaba/MG | C6: Geisa Costa e Marco Aurélio (cofundadores) | D6: +55 11 94445-2686 | E6: sp@artbeautycenter.com.br | F6: https://www.artbeautycenter.com.br/ | G6: Pesquisa pública | H6: Prospectar | I6: Site já apresenta bem a clínica; oportunidade provável em solicitações de consulta e acompanhamento entre unidades. | L6: Confirmar origem dos proprietários e perguntar se já usam sistema de agenda. | M6: A confirmar | R6: WhatsApp de agendamento de São Paulo. Há divergência em outros telefones do rodapé; não foram usados. | S6: =IF(A6="","",IF(H6="Fechado","Fechado",IF(H6="Perdido","Perdido",IF(K6="","Sem data",IF(K6<TODAY(),"Atrasado",IF(K6=TODAY(),"Hoje","Agendado"))))))) -> Sem data | T6: WhatsApp | U6: +55 11 94445-2686 | V6: https://www.artbeautycenter.com.br/ | W6: https://www.artbeautycenter.com.br/sobre-nos | X6: 46302 | Y6: Verificado | Z6: 6 | AA6: 8 | AB6: Site já apresenta bem a clínica; oportunidade provável em solicitações de consulta e acompanhamento entre unidades. | AC6: Duas unidades, equipe multidisciplinar e cargos de marketing/finanças publicados; capacidade financeira real desconhecida. | AD6: =IF(A6="","",IF(OR(AK6<>"Qualificado",Y6<>"Verificado",U6="",Z6="",AA6=""),"Pendente",IF(AND(Z6>=7,AA6>=6),"Alta",IF(AND(Z6>=5,AA6>=4),"Média","Baixa")))) -> Pendente | AE6: Brasil | AF6: Geisa Costa e Marco Aurélio (cofundadores) | AG6: Não confirmado | AH6: https://www.artbeautycenter.com.br/sobre-nos | AI6: Brasil | AJ6: Média | AK6: Pendente | AL6: Confirmar proprietário/origem brasileira
A7: Danielle Oliveira Estética Avançada | B7: São Paulo/SP | C7: Danielle Oliveira (cofundadora) | D7: +55 11 97176-0036 | E7: contato@danielleoliveira.com.br | F7: https://www.danielleoliveira.com.br/ | G7: Pesquisa pública | H7: Prospectar | I7: Agendamento encaminhado ao WhatsApp; múltiplas unidades podem se beneficiar de catálogo e gestão por unidade. | L7: Confirmar proprietária brasileira e autonomia para contratar; oferecer piloto em uma unidade. | M7: A confirmar | R7: Contato da unidade Limão; contato@danielleoliveira.com.br. Formação no Brasil não comprova nacionalidade. | S7: =IF(A7="","",IF(H7="Fechado","Fechado",IF(H7="Perdido","Perdido",IF(K7="","Sem data",IF(K7<TODAY(),"Atrasado",IF(K7=TODAY(),"Hoje","Agendado"))))))) -> Sem data | T7: WhatsApp | U7: +55 11 97176-0036 | V7: https://www.danielleoliveira.com.br/ | W7: https://www.danielleoliveira.com.br/ | X7: 46302 | Y7: Verificado | Z7: 7 | AA7: 8 | AB7: Agendamento encaminhado ao WhatsApp; múltiplas unidades podem se beneficiar de catálogo e gestão por unidade. | AC7: Cinco unidades listadas; três próprias declaradas no texto institucional. Variedade de procedimentos e estrutura de franquias. | AD7: =IF(A7="","",IF(OR(AK7<>"Qualificado",Y7<>"Verificado",U7="",Z7="",AA7=""),"Pendente",IF(AND(Z7>=7,AA7>=6),"Alta",IF(AND(Z7>=5,AA7>=4),"Média","Baixa")))) -> Pendente | AE7: Brasil | AF7: Danielle Oliveira (cofundadora) | AG7: Não confirmado | AH7: https://www.danielleoliveira.com.br/ | AI7: Brasil | AJ7: Média | AK7: Pendente | AL7: Confirmar proprietário/origem brasileira
A8: JK Estética Avançada | B8: São Paulo/SP; Rio de Janeiro/RJ | C8: Não identificado | F8: https://www.jkesteticaavancada.com.br/ | G8: Pesquisa pública | H8: Prospectar | I8: Site elaborado e amplo catálogo; avaliar integração da consulta com acompanhamento e painel antes de propor substituição. | L8: Identificar gestor/proprietário brasileiro e confirmar canal para proposta comercial. | M8: A confirmar | R8: contato@jkesteticaavancada.com.br é divulgado como Ouvidoria; não foi tratado como endereço de vendas. | S8: =IF(A8="","",IF(H8="Fechado","Fechado",IF(H8="Perdido","Perdido",IF(K8="","Sem data",IF(K8<TODAY(),"Atrasado",IF(K8=TODAY(),"Hoje","Agendado"))))))) -> Sem data | T8: Formulário | U8: Formulário de consulta no site | V8: https://www.jkesteticaavancada.com.br/ | W8: https://www.jkesteticaavancada.com.br/ | X8: 46302 | Y8: Verificado | Z8: 5 | AA8: 8 | AB8: Site elaborado e amplo catálogo; avaliar integração da consulta com acompanhamento e painel antes de propor substituição. | AC8: Endereços em SP e RJ, serviços e tecnologias variados divulgados; orçamento não foi informado. | AD8: =IF(A8="","",IF(OR(AK8<>"Qualificado",Y8<>"Verificado",U8="",Z8="",AA8=""),"Pendente",IF(AND(Z8>=7,AA8>=6),"Alta",IF(AND(Z8>=5,AA8>=4),"Média","Baixa")))) -> Pendente | AE8: Brasil | AF8: Não identificado | AG8: Não confirmado | AI8: Brasil | AJ8: Média | AK8: Pendente | AL8: Confirmar proprietário/origem brasileira
A9: Clinic Aesthetica Group | B9: São Paulo/SP | C9: Alline Ortiz (proprietária/CEO) | D9: +55 11 97346-9977 | E9: atendimento@clinicspa.com.br | F9: https://www.clinicspa.com.br/ | G9: Pesquisa pública | H9: Prospectar | I9: Já existe calendário/formulário de avaliação no site. Oferecer integração e área do cliente somente se faltar no processo atual. | L9: Confirmar proprietária brasileira e descobrir quais sistemas já utilizam. | M9: A confirmar | R9: Não apresentar como clínica com agendamento apenas por WhatsApp; atendimento@clinicspa.com.br. | S9: =IF(A9="","",IF(H9="Fechado","Fechado",IF(H9="Perdido","Perdido",IF(K9="","Sem data",IF(K9<TODAY(),"Atrasado",IF(K9=TODAY(),"Hoje","Agendado"))))))) -> Sem data | T9: WhatsApp | U9: +55 11 97346-9977 | V9: https://www.clinicspa.com.br/ | W9: https://www.clinicspa.com.br/ | X9: 46302 | Y9: Verificado | Z9: 4 | AA9: 7 | AB9: Já existe calendário/formulário de avaliação no site. Oferecer integração e área do cliente somente se faltar no processo atual. | AC9: Site anuncia 12 anos de atuação, equipe e linhas de tratamento; sinais de operação estruturada. | AD9: =IF(A9="","",IF(OR(AK9<>"Qualificado",Y9<>"Verificado",U9="",Z9="",AA9=""),"Pendente",IF(AND(Z9>=7,AA9>=6),"Alta",IF(AND(Z9>=5,AA9>=4),"Média","Baixa")))) -> Pendente | AE9: Brasil | AF9: Alline Ortiz (proprietária/CEO) | AG9: Não confirmado | AH9: https://www.clinicspa.com.br/ | AI9: Brasil | AJ9: Média | AK9: Pendente | AL9: Confirmar proprietário/origem brasileira
A10: Derma Mais | B10: Londrina/PR | C10: Marina Mouco Valotto (razão social; vínculo societário a confirmar) | D10: +55 43 99162-2868 | F10: https://clinicaesteticalondrina.com.br/ | G10: Pesquisa pública | H10: Prospectar | I10: Site direciona conversa após coleta de nome e telefone; acompanhamento capilar/facial combina com área privada do cliente. | L10: Confirmar sócios brasileiros e avaliar solicitação de consulta com aprovação da equipe. | M10: A confirmar | R10: CNPJ 31.219.709/0001-06. Liderança técnica não foi automaticamente considerada propriedade. | S10: =IF(A10="","",IF(H10="Fechado","Fechado",IF(H10="Perdido","Perdido",IF(K10="","Sem data",IF(K10<TODAY(),"Atrasado",IF(K10=TODAY(),"Hoje","Agendado"))))))) -> Sem data | T10: WhatsApp | U10: +55 43 99162-2868 | V10: https://clinicaesteticalondrina.com.br/ | W10: https://clinicaesteticalondrina.com.br/quem-somos/ | X10: 46302 | Y10: Verificado | Z10: 7 | AA10: 7 | AB10: Site direciona conversa após coleta de nome e telefone; acompanhamento capilar/facial combina com área privada do cliente. | AC10: Equipe clínica, financeira e relacionamento identificada; tratamentos capilares/faciais/corporais e unidade física. | AD10: =IF(A10="","",IF(OR(AK10<>"Qualificado",Y10<>"Verificado",U10="",Z10="",AA10=""),"Pendente",IF(AND(Z10>=7,AA10>=6),"Alta",IF(AND(Z10>=5,AA10>=4),"Média","Baixa")))) -> Pendente | AE10: Brasil | AF10: Marina Mouco Valotto (razão social; vínculo societário a confirmar) | AG10: Não confirmado | AH10: https://clinicaesteticalondrina.com.br/quem-somos/ | AI10: Brasil | AJ10: Média | AK10: Pendente | AL10: Confirmar proprietário/origem brasileira
A11: Pró-Corpo | B11: Rede em SP, RJ e PR | C11: Não identificado | D11: +55 11 4118-9955 | F11: https://www.procorpoestetica.com.br/ | G11: Pesquisa pública | H11: Prospectar | I11: Já possui comércio eletrônico e formulário de solicitação de agendamento. Venda simples de site tem baixa aderência; investigar integração. | L11: Confirmar proprietário brasileiro e acesso ao decisor; priorizar depois das clínicas independentes. | M11: A confirmar | R11: Capacidade estimada alta não significa maior facilidade de venda. | S11: =IF(A11="","",IF(H11="Fechado","Fechado",IF(H11="Perdido","Perdido",IF(K11="","Sem data",IF(K11<TODAY(),"Atrasado",IF(K11=TODAY(),"Hoje","Agendado"))))))) -> Sem data | T11: WhatsApp | U11: +55 11 4118-9955 | V11: https://www.procorpoestetica.com.br/ | W11: https://www.procorpoestetica.com.br/ | X11: 46302 | Y11: Verificado | Z11: 3 | AA11: 9 | AB11: Já possui comércio eletrônico e formulário de solicitação de agendamento. Venda simples de site tem baixa aderência; investigar integração. | AC11: Rede de unidades, catálogo amplo, preços e comércio eletrônico publicados; contratação provavelmente exige avaliação corporativa. | AD11: =IF(A11="","",IF(OR(AK11<>"Qualificado",Y11<>"Verificado",U11="",Z11="",AA11=""),"Pendente",IF(AND(Z11>=7,AA11>=6),"Alta",IF(AND(Z11>=5,AA11>=4),"Média","Baixa")))) -> Pendente | AE11: Brasil | AF11: Não identificado | AG11: Não confirmado | AI11: Brasil | AJ11: Média | AK11: Pendente | AL11: Confirmar proprietário/origem brasileira
A12: Natalia Beauty Clinic | B12: São Paulo/SP; Barueri/SP; Curitiba/PR | C12: Natalia Martins | F12: https://nataliabeauty.com.br/clinica/ | G12: Pesquisa pública | H12: Prospectar | I12: Site e marca maduros; unidades encaminham atendimento para WhatsApp. Oferecer integração e experiência do cliente, sem desvalorizar o site atual. | L12: Pedir contato da gestão e verificar sistema atual antes de oferecer demonstração. | M12: A confirmar | R12: Biografia oficial: “Natural da capital de São Paulo”. Origem brasileira documentada, sem verificação de documentos de cidadania. Não usar WhatsApp da agência no rodapé. | S12: =IF(A12="","",IF(H12="Fechado","Fechado",IF(H12="Perdido","Perdido",IF(K12="","Sem data",IF(K12<TODAY(),"Atrasado",IF(K12=TODAY(),"Hoje","Agendado"))))))) -> Sem data | T12: Telefone | U12: +55 11 3061-2670 | V12: https://nataliabeauty.com.br/clinica/ | W12: https://nataliabeauty.com.br/clinica/ | X12: 46302 | Y12: Verificado | Z12: 4 | AA12: 9 | AB12: Site e marca maduros; unidades encaminham atendimento para WhatsApp. Oferecer integração e experiência do cliente, sem desvalorizar o site atual. | AC12: Três unidades listadas e matriz de 1.000 m² anunciada; equipe e negócios complementares. Não estima disponibilidade de caixa. | AD12: =IF(A12="","",IF(OR(AK12<>"Qualificado",Y12<>"Verificado",U12="",Z12="",AA12=""),"Pendente",IF(AND(Z12>=7,AA12>=6),"Alta",IF(AND(Z12>=5,AA12>=4),"Média","Baixa")))) -> Baixa | AE12: Brasil | AF12: Natalia Martins | AG12: Origem brasileira documentada | AH12: https://nataliabeauty.com.br/quem-somos/ | AI12: Brasil | AJ12: Média | AK12: Qualificado
A13: SPA Renata França | B13: São Paulo/SP | C13: Renata França | D13: +55 11 99129-9556 | E13: contato@renatafranca.com | F13: https://www.sparenatafranca.com/sobre/ | G13: Pesquisa pública | H13: Prospectar | I13: Contato para atendimento no WhatsApp; área de alunos já existe. Investigar se pacientes possuem agendamento e acompanhamento próprios. | L13: Solicitar contato da gestão do SPA e oferecer organização das solicitações de consulta. | M13: A confirmar | R13: Biografia oficial identifica Ilhéus/BA como cidade natal (“hometown”). Origem brasileira documentada, cidadania legal não verificada. Não usar números de cursos ou venda corporativa. | S13: =IF(A13="","",IF(H13="Fechado","Fechado",IF(H13="Perdido","Perdido",IF(K13="","Sem data",IF(K13<TODAY(),"Atrasado",IF(K13=TODAY(),"Hoje","Agendado"))))))) -> Sem data | T13: WhatsApp | U13: +55 11 99129-9556 | V13: https://www.sparenatafranca.com/sobre/ | W13: https://www.sparenatafranca.com/nossa-historia/renata | X13: 46302 | Y13: Verificado | Z13: 6 | AA13: 8 | AB13: Contato para atendimento no WhatsApp; área de alunos já existe. Investigar se pacientes possuem agendamento e acompanhamento próprios. | AC13: Marca com protocolos próprios, equipe e operação de formação/loja; capacidade de compra é hipótese baseada na estrutura. | AD13: =IF(A13="","",IF(OR(AK13<>"Qualificado",Y13<>"Verificado",U13="",Z13="",AA13=""),"Pendente",IF(AND(Z13>=7,AA13>=6),"Alta",IF(AND(Z13>=5,AA13>=4),"Média","Baixa")))) -> Média | AE13: Brasil | AF13: Renata França | AG13: Origem brasileira documentada | AH13: https://www.sparenatafranca.com/nossa-historia/renata | AI13: Brasil | AJ13: Média | AK13: Qualificado
A14: VitaSmile | B14: Londres | C14: Não identificado | D14: +44 7848 958312 | F14: https://www.vitasmile.co.uk/ | G14: Pesquisa pública | H14: Prospectar | I14: Clínica odontológica também oferece rejuvenescimento facial; integração de atendimento pode ser útil, mas demanda difere de estética pura. | L14: Confirmar se o proprietário é brasileiro e se há interesse específico na frente de estética. | M14: A confirmar | R14: FORA DO BRASIL. “Clínica brasileira” e atendimento em português não comprovam nacionalidade do dono. | S14: =IF(A14="","",IF(H14="Fechado","Fechado",IF(H14="Perdido","Perdido",IF(K14="","Sem data",IF(K14<TODAY(),"Atrasado",IF(K14=TODAY(),"Hoje","Agendado"))))))) -> Sem data | T14: WhatsApp | U14: +44 7848 958312 | V14: https://www.vitasmile.co.uk/ | W14: https://www.vitasmile.co.uk/estetica-que-respeita-voce/ | X14: 46302 | Y14: Verificado | Z14: 5 | AA14: 7 | AB14: Clínica odontológica também oferece rejuvenescimento facial; integração de atendimento pode ser útil, mas demanda difere de estética pura. | AC14: Equipe, serviços odontológicos e estética facial, site com preços/financiamento publicados. | AD14: =IF(A14="","",IF(OR(AK14<>"Qualificado",Y14<>"Verificado",U14="",Z14="",AA14=""),"Pendente",IF(AND(Z14>=7,AA14>=6),"Alta",IF(AND(Z14>=5,AA14>=4),"Média","Baixa")))) -> Pendente | AE14: Reino Unido | AF14: Não identificado | AG14: Não confirmado | AI14: FORA DO BRASIL | AJ14: Média | AK14: Pendente | AL14: Confirmar proprietário/origem brasileira
A15: Maison B | B15: Lisboa | C15: Anni Frota | G15: Pesquisa pública | H15: Prospectar | I15: Espaço de estética com tratamentos naturais e quatro salas descrito em reportagem; site e agenda atuais não verificados. | L15: Revalidar funcionamento, telefone e proprietária antes de qualquer abordagem. | M15: A confirmar | R15: FORA DO BRASIL. Reportagem de 22/12/2022. Não presumir que telefone aceita WhatsApp nem que contato continua ativo. | S15: =IF(A15="","",IF(H15="Fechado","Fechado",IF(H15="Perdido","Perdido",IF(K15="","Sem data",IF(K15<TODAY(),"Atrasado",IF(K15=TODAY(),"Hoje","Agendado"))))))) -> Sem data | T15: Telefone | U15: +351 912 349 066 | W15: https://www.nit.pt/compras/maison-b-o-novo-espaco-de-beleza-em-lisboa-onde-todos-os-tratamentos-sao-naturais | X15: 46302 | Y15: Pendente | Z15: 6 | AA15: 6 | AB15: Espaço de estética com tratamentos naturais e quatro salas descrito em reportagem; site e agenda atuais não verificados. | AC15: Estrutura de quatro salas e serviços publicados em 2022. Evidência histórica, sem validação financeira atual. | AD15: =IF(A15="","",IF(OR(AK15<>"Qualificado",Y15<>"Verificado",U15="",Z15="",AA15=""),"Pendente",IF(AND(Z15>=7,AA15>=6),"Alta",IF(AND(Z15>=5,AA15>=4),"Média","Baixa")))) -> Pendente | AE15: Portugal | AF15: Anni Frota | AG15: Brasileira explícita em fonte | AH15: https://www.nit.pt/compras/maison-b-o-novo-espaco-de-beleza-em-lisboa-onde-todos-os-tratamentos-sao-naturais | AI15: FORA DO BRASIL | AJ15: Baixa | AK15: Pendente | AL15: Revalidar contato/atividade atual
A16: Bellavish Aesthetic Clinic | B16: Dublin | C16: Phamela Priscila Bezerra | G16: Pesquisa pública | H16: Prospectar | I16: Clínica de estética descrita em matéria institucional; jornada digital atual não pôde ser validada. | L16: Revalidar atividade e telefone; confirmar responsável atual. | M16: A confirmar | R16: FORA DO BRASIL. Fonte de 21/09/2022: nasceu em Londrina/PR. E-mail ofuscado não foi inventado. Domínio antigo não foi considerado site atual. | S16: =IF(A16="","",IF(H16="Fechado","Fechado",IF(H16="Perdido","Perdido",IF(K16="","Sem data",IF(K16<TODAY(),"Atrasado",IF(K16=TODAY(),"Hoje","Agendado"))))))) -> Sem data | T16: Telefone | U16: +353 89 607 6938 | W16: https://nepuga.edu.br/news/biomedica-esteta-europa/ | X16: 46302 | Y16: Pendente | Z16: 6 | AA16: 6 | AB16: Clínica de estética descrita em matéria institucional; jornada digital atual não pôde ser validada. | AC16: Experiência e operação clínica descritas em 2022; sinal histórico insuficiente para inferir orçamento atual. | AD16: =IF(A16="","",IF(OR(AK16<>"Qualificado",Y16<>"Verificado",U16="",Z16="",AA16=""),"Pendente",IF(AND(Z16>=7,AA16>=6),"Alta",IF(AND(Z16>=5,AA16>=4),"Média","Baixa")))) -> Pendente | AE16: Irlanda | AF16: Phamela Priscila Bezerra | AG16: Origem brasileira documentada | AH16: https://nepuga.edu.br/news/biomedica-esteta-europa/ | AI16: FORA DO BRASIL | AJ16: Baixa | AK16: Pendente | AL16: Revalidar contato/atividade atual
A17: Brazilicious Beauty Spa | B17: Austin/Texas (referência histórica) | C17: Josie Rushing | F17: https://braziliciousbeautyspa.com/ | G17: Pesquisa pública | H17: Prospectar | I17: Proprietária brasileira identificada em reportagem; contato comercial atual e experiência do site não puderam ser verificados. | L17: Localizar fonte atual de contato comercial; manter fora da fila de abordagem. | M17: A confirmar | R17: FORA DO BRASIL. Reportagem de 29/04/2022; site bloqueou acesso automatizado. brazilicious.com é comércio de pão de queijo e não pertence a este registro. | S17: =IF(A17="","",IF(H17="Fechado","Fechado",IF(H17="Perdido","Perdido",IF(K17="","Sem data",IF(K17<TODAY(),"Atrasado",IF(K17=TODAY(),"Hoje","Agendado"))))))) -> Sem data | X17: 46302 | Y17: Pendente | AB17: Proprietária brasileira identificada em reportagem; contato comercial atual e experiência do site não puderam ser verificados. | AC17: Não pontuado: faturamento histórico de reportagem não comprova orçamento atual. | AD17: =IF(A17="","",IF(OR(AK17<>"Qualificado",Y17<>"Verificado",U17="",Z17="",AA17=""),"Pendente",IF(AND(Z17>=7,AA17>=6),"Alta",IF(AND(Z17>=5,AA17>=4),"Média","Baixa")))) -> Pendente | AE17: Estados Unidos | AF17: Josie Rushing | AG17: Brasileira explícita em fonte | AH17: https://revistapegn.globo.com/Mulheres-empreendedoras/noticia/2022/04/brasileira-fatura-r-2-milhoes-com-drenagem-linfatica-nos-eua.html | AI17: FORA DO BRASIL | AJ17: Não atribuída | AK17: Pendente | AL17: Localizar contato comercial atual fora do Instagram
S18: =IF(A18="","",IF(H18="Fechado","Fechado",IF(H18="Perdido","Perdido",IF(K18="","Sem data",IF(K18<TODAY(),"Atrasado",IF(K18=TODAY(),"Hoje","Agendado"))))))) | AD18: =IF(A18="","",IF(OR(AK18<>"Qualificado",Y18<>"Verificado",U18="",Z18="",AA18=""),"Pendente",IF(AND(Z18>=7,AA18>=6),"Alta",IF(AND(Z18>=5,AA18>=4),"Média","Baixa"))))
S19: =IF(A19="","",IF(H19="Fechado","Fechado",IF(H19="Perdido","Perdido",IF(K19="","Sem data",IF(K19<TODAY(),"Atrasado",IF(K19=TODAY(),"Hoje","Agendado"))))))) | AD19: =IF(A19="","",IF(OR(AK19<>"Qualificado",Y19<>"Verificado",U19="",Z19="",AA19=""),"Pendente",IF(AND(Z19>=7,AA19>=6),"Alta",IF(AND(Z19>=5,AA19>=4),"Média","Baixa"))))
S20: =IF(A20="","",IF(H20="Fechado","Fechado",IF(H20="Perdido","Perdido",IF(K20="","Sem data",IF(K20<TODAY(),"Atrasado",IF(K20=TODAY(),"Hoje","Agendado"))))))) | AD20: =IF(A20="","",IF(OR(AK20<>"Qualificado",Y20<>"Verificado",U20="",Z20="",AA20=""),"Pendente",IF(AND(Z20>=7,AA20>=6),"Alta",IF(AND(Z20>=5,AA20>=4),"Média","Baixa"))))
S21: =IF(A21="","",IF(H21="Fechado","Fechado",IF(H21="Perdido","Perdido",IF(K21="","Sem data",IF(K21<TODAY(),"Atrasado",IF(K21=TODAY(),"Hoje","Agendado"))))))) | AD21: =IF(A21="","",IF(OR(AK21<>"Qualificado",Y21<>"Verificado",U21="",Z21="",AA21=""),"Pendente",IF(AND(Z21>=7,AA21>=6),"Alta",IF(AND(Z21>=5,AA21>=4),"Média","Baixa"))))
S22: =IF(A22="","",IF(H22="Fechado","Fechado",IF(H22="Perdido","Perdido",IF(K22="","Sem data",IF(K22<TODAY(),"Atrasado",IF(K22=TODAY(),"Hoje","Agendado"))))))) | AD22: =IF(A22="","",IF(OR(AK22<>"Qualificado",Y22<>"Verificado",U22="",Z22="",AA22=""),"Pendente",IF(AND(Z22>=7,AA22>=6),"Alta",IF(AND(Z22>=5,AA22>=4),"Média","Baixa"))))
S23: =IF(A23="","",IF(H23="Fechado","Fechado",IF(H23="Perdido","Perdido",IF(K23="","Sem data",IF(K23<TODAY(),"Atrasado",IF(K23=TODAY(),"Hoje","Agendado"))))))) | AD23: =IF(A23="","",IF(OR(AK23<>"Qualificado",Y23<>"Verificado",U23="",Z23="",AA23=""),"Pendente",IF(AND(Z23>=7,AA23>=6),"Alta",IF(AND(Z23>=5,AA23>=4),"Média","Baixa"))))
S24: =IF(A24="","",IF(H24="Fechado","Fechado",IF(H24="Perdido","Perdido",IF(K24="","Sem data",IF(K24<TODAY(),"Atrasado",IF(K24=TODAY(),"Hoje","Agendado"))))))) | AD24: =IF(A24="","",IF(OR(AK24<>"Qualificado",Y24<>"Verificado",U24="",Z24="",AA24=""),"Pendente",IF(AND(Z24>=7,AA24>=6),"Alta",IF(AND(Z24>=5,AA24>=4),"Média","Baixa"))))
S25: =IF(A25="","",IF(H25="Fechado","Fechado",IF(H25="Perdido","Perdido",IF(K25="","Sem data",IF(K25<TODAY(),"Atrasado",IF(K25=TODAY(),"Hoje","Agendado"))))))) | AD25: =IF(A25="","",IF(OR(AK25<>"Qualificado",Y25<>"Verificado",U25="",Z25="",AA25=""),"Pendente",IF(AND(Z25>=7,AA25>=6),"Alta",IF(AND(Z25>=5,AA25>=4),"Média","Baixa"))))
S26: =IF(A26="","",IF(H26="Fechado","Fechado",IF(H26="Perdido","Perdido",IF(K26="","Sem data",IF(K26<TODAY(),"Atrasado",IF(K26=TODAY(),"Hoje","Agendado"))))))) | AD26: =IF(A26="","",IF(OR(AK26<>"Qualificado",Y26<>"Verificado",U26="",Z26="",AA26=""),"Pendente",IF(AND(Z26>=7,AA26>=6),"Alta",IF(AND(Z26>=5,AA26>=4),"Média","Baixa"))))
S27: =IF(A27="","",IF(H27="Fechado","Fechado",IF(H27="Perdido","Perdido",IF(K27="","Sem data",IF(K27<TODAY(),"Atrasado",IF(K27=TODAY(),"Hoje","Agendado"))))))) | AD27: =IF(A27="","",IF(OR(AK27<>"Qualificado",Y27<>"Verificado",U27="",Z27="",AA27=""),"Pendente",IF(AND(Z27>=7,AA27>=6),"Alta",IF(AND(Z27>=5,AA27>=4),"Média","Baixa"))))
S28: =IF(A28="","",IF(H28="Fechado","Fechado",IF(H28="Perdido","Perdido",IF(K28="","Sem data",IF(K28<TODAY(),"Atrasado",IF(K28=TODAY(),"Hoje","Agendado"))))))) | AD28: =IF(A28="","",IF(OR(AK28<>"Qualificado",Y28<>"Verificado",U28="",Z28="",AA28=""),"Pendente",IF(AND(Z28>=7,AA28>=6),"Alta",IF(AND(Z28>=5,AA28>=4),"Média","Baixa"))))
S29: =IF(A29="","",IF(H29="Fechado","Fechado",IF(H29="Perdido","Perdido",IF(K29="","Sem data",IF(K29<TODAY(),"Atrasado",IF(K29=TODAY(),"Hoje","Agendado"))))))) | AD29: =IF(A29="","",IF(OR(AK29<>"Qualificado",Y29<>"Verificado",U29="",Z29="",AA29=""),"Pendente",IF(AND(Z29>=7,AA29>=6),"Alta",IF(AND(Z29>=5,AA29>=4),"Média","Baixa"))))
... S204: =IF(A204="","",IF(H204="Fechado","Fechado",IF(H204="Perdido","Perdido",IF(K204="","Sem data",IF(K204<TODAY(),"Atrasado",IF(K204=TODAY(),"Hoje","Agendado"))))))) | AD204: =IF(A204="","",IF(OR(AK204<>"Qualificado",Y204<>"Verificado",U204="",Z204="",AA204=""),"Pendente",IF(AND(Z204>=7,AA204>=6),"Alta",IF(AND(Z204>=5,AA204>=4),"Média","Baixa"))))

Sheet Qualificados
A1: CRM de clínicas • Qualificados
A2: Pesquisa em 07/10/2026. Notas estimadas por evidências públicas; sem contato enviado. Edite sua cópia na aba CRM. Abas Qualificados/Pendentes são retratos da pesquisa.
A4: Clínica | B4: Cidade/UF | C4: Responsável | D4: WhatsApp comercial | E4: E-mail comercial | F4: Instagram/site | G4: Origem | H4: Etapa | I4: Interesse/necessidade | J4: Último contato | K4: Próximo contato | L4: Próxima ação | M4: Preferência de contato | N4: Implantação proposta R$ | O4: Mensalidade proposta R$ | P4: Data fechamento | Q4: Motivo perda | R4: Observações | S4: Situação retorno | T4: Canal principal | U4: Contato principal | V4: Site verificado | W4: Fonte pública contato | X4: Data verificação | Y4: Verificação | Z4: Potencial 0–10 | AA4: Capacidade estimada 0–10 | AB4: Evidências potencial | AC4: Evidências capacidade | AD4: Prioridade | AE4: País clínica | AF4: Proprietário identificado | AG4: Proprietário brasileiro? | AH4: Fonte proprietário/origem | AI4: Localização | AJ4: Confiança da capacidade | AK4: Qualificação | AL4: Pendência
A5: Natalia Beauty Clinic | B5: São Paulo/SP; Barueri/SP; Curitiba/PR | C5: Natalia Martins | F5: https://nataliabeauty.com.br/clinica/ | G5: Pesquisa pública | H5: Prospectar | I5: Site e marca maduros; unidades encaminham atendimento para WhatsApp. Oferecer integração e experiência do cliente, sem desvalorizar o site atual. | L5: Pedir contato da gestão e verificar sistema atual antes de oferecer demonstração. | M5: A confirmar | R5: Biografia oficial: “Natural da capital de São Paulo”. Origem brasileira documentada, sem verificação de documentos de cidadania. Não usar WhatsApp da agência no rodapé. | S5: Sem data | T5: Telefone | U5: +55 11 3061-2670 | V5: https://nataliabeauty.com.br/clinica/ | W5: https://nataliabeauty.com.br/clinica/ | X5: 46302 | Y5: Verificado | Z5: 4 | AA5: 9 | AB5: Site e marca maduros; unidades encaminham atendimento para WhatsApp. Oferecer integração e experiência do cliente, sem desvalorizar o site atual. | AC5: Três unidades listadas e matriz de 1.000 m² anunciada; equipe e negócios complementares. Não estima disponibilidade de caixa. | AD5: Baixa | AE5: Brasil | AF5: Natalia Martins | AG5: Origem brasileira documentada | AH5: https://nataliabeauty.com.br/quem-somos/ | AI5: Brasil | AJ5: Média | AK5: Qualificado
A6: SPA Renata França | B6: São Paulo/SP | C6: Renata França | D6: +55 11 99129-9556 | E6: contato@renatafranca.com | F6: https://www.sparenatafranca.com/sobre/ | G6: Pesquisa pública | H6: Prospectar | I6: Contato para atendimento no WhatsApp; área de alunos já existe. Investigar se pacientes possuem agendamento e acompanhamento próprios. | L6: Solicitar contato da gestão do SPA e oferecer organização das solicitações de consulta. | M6: A confirmar | R6: Biografia oficial identifica Ilhéus/BA como cidade natal (“hometown”). Origem brasileira documentada, cidadania legal não verificada. Não usar números de cursos ou venda corporativa. | S6: Sem data | T6: WhatsApp | U6: +55 11 99129-9556 | V6: https://www.sparenatafranca.com/sobre/ | W6: https://www.sparenatafranca.com/nossa-historia/renata | X6: 46302 | Y6: Verificado | Z6: 6 | AA6: 8 | AB6: Contato para atendimento no WhatsApp; área de alunos já existe. Investigar se pacientes possuem agendamento e acompanhamento próprios. | AC6: Marca com protocolos próprios, equipe e operação de formação/loja; capacidade de compra é hipótese baseada na estrutura. | AD6: Média | AE6: Brasil | AF6: Renata França | AG6: Origem brasileira documentada | AH6: https://www.sparenatafranca.com/nossa-historia/renata | AI6: Brasil | AJ6: Média | AK6: Qualificado

Sheet Pendentes
A1: CRM de clínicas • Pendentes
A2: Pesquisa em 07/10/2026. Notas estimadas por evidências públicas; sem contato enviado. Edite sua cópia na aba CRM. Abas Qualificados/Pendentes são retratos da pesquisa.
A4: Clínica | B4: Cidade/UF | C4: Responsável | D4: WhatsApp comercial | E4: E-mail comercial | F4: Instagram/site | G4: Origem | H4: Etapa | I4: Interesse/necessidade | J4: Último contato | K4: Próximo contato | L4: Próxima ação | M4: Preferência de contato | N4: Implantação proposta R$ | O4: Mensalidade proposta R$ | P4: Data fechamento | Q4: Motivo perda | R4: Observações | S4: Situação retorno | T4: Canal principal | U4: Contato principal | V4: Site verificado | W4: Fonte pública contato | X4: Data verificação | Y4: Verificação | Z4: Potencial 0–10 | AA4: Capacidade estimada 0–10 | AB4: Evidências potencial | AC4: Evidências capacidade | AD4: Prioridade | AE4: País clínica | AF4: Proprietário identificado | AG4: Proprietário brasileiro? | AH4: Fonte proprietário/origem | AI4: Localização | AJ4: Confiança da capacidade | AK4: Qualificação | AL4: Pendência
A5: Instituto Remodele | B5: São Paulo/SP | C5: Não identificado | D5: +55 11 91907-8160 | E5: contato@remodele.com.br | F5: https://remodele.com.br/ | G5: Pesquisa pública | H5: Prospectar | I5: Chamadas de agendamento levam ao WhatsApp; catálogo facial e corporal permite apresentar site com solicitações de consulta e painel. | L5: Confirmar proprietário brasileiro; apresentar fluxo de agendamento e edição dos serviços. | M5: A confirmar | R5: CNPJ 63.154.444/0001-00; contato@remodele.com.br. Não confundir com Instituto Remodele de Rio Preto. | S5: Sem data | T5: WhatsApp | U5: +55 11 91907-8160 | V5: https://remodele.com.br/ | W5: https://remodele.com.br/assets/index-ClmuxGc9.js | X5: 46302 | Y5: Verificado | Z5: 8 | AA5: 5 | AB5: Chamadas de agendamento levam ao WhatsApp; catálogo facial e corporal permite apresentar site com solicitações de consulta e painel. | AC5: Site próprio e endereço físico publicados; equipe, unidades adicionais e investimento disponíveis não comprovados. | AD5: Pendente | AE5: Brasil | AF5: Não identificado | AG5: Não confirmado | AI5: Brasil | AJ5: Média | AK5: Pendente | AL5: Confirmar proprietário/origem brasileira
A6: Art Beauty Center | B6: São Paulo/SP; Uberaba/MG | C6: Geisa Costa e Marco Aurélio (cofundadores) | D6: +55 11 94445-2686 | E6: sp@artbeautycenter.com.br | F6: https://www.artbeautycenter.com.br/ | G6: Pesquisa pública | H6: Prospectar | I6: Site já apresenta bem a clínica; oportunidade provável em solicitações de consulta e acompanhamento entre unidades. | L6: Confirmar origem dos proprietários e perguntar se já usam sistema de agenda. | M6: A confirmar | R6: WhatsApp de agendamento de São Paulo. Há divergência em outros telefones do rodapé; não foram usados. | S6: Sem data | T6: WhatsApp | U6: +55 11 94445-2686 | V6: https://www.artbeautycenter.com.br/ | W6: https://www.artbeautycenter.com.br/sobre-nos | X6: 46302 | Y6: Verificado | Z6: 6 | AA6: 8 | AB6: Site já apresenta bem a clínica; oportunidade provável em solicitações de consulta e acompanhamento entre unidades. | AC6: Duas unidades, equipe multidisciplinar e cargos de marketing/finanças publicados; capacidade financeira real desconhecida. | AD6: Pendente | AE6: Brasil | AF6: Geisa Costa e Marco Aurélio (cofundadores) | AG6: Não confirmado | AH6: https://www.artbeautycenter.com.br/sobre-nos | AI6: Brasil | AJ6: Média | AK6: Pendente | AL6: Confirmar proprietário/origem brasileira
A7: Danielle Oliveira Estética Avançada | B7: São Paulo/SP | C7: Danielle Oliveira (cofundadora) | D7: +55 11 97176-0036 | E7: contato@danielleoliveira.com.br | F7: https://www.danielleoliveira.com.br/ | G7: Pesquisa pública | H7: Prospectar | I7: Agendamento encaminhado ao WhatsApp; múltiplas unidades podem se beneficiar de catálogo e gestão por unidade. | L7: Confirmar proprietária brasileira e autonomia para contratar; oferecer piloto em uma unidade. | M7: A confirmar | R7: Contato da unidade Limão; contato@danielleoliveira.com.br. Formação no Brasil não comprova nacionalidade. | S7: Sem data | T7: WhatsApp | U7: +55 11 97176-0036 | V7: https://www.danielleoliveira.com.br/ | W7: https://www.danielleoliveira.com.br/ | X7: 46302 | Y7: Verificado | Z7: 7 | AA7: 8 | AB7: Agendamento encaminhado ao WhatsApp; múltiplas unidades podem se beneficiar de catálogo e gestão por unidade. | AC7: Cinco unidades listadas; três próprias declaradas no texto institucional. Variedade de procedimentos e estrutura de franquias. | AD7: Pendente | AE7: Brasil | AF7: Danielle Oliveira (cofundadora) | AG7: Não confirmado | AH7: https://www.danielleoliveira.com.br/ | AI7: Brasil | AJ7: Média | AK7: Pendente | AL7: Confirmar proprietário/origem brasileira
A8: JK Estética Avançada | B8: São Paulo/SP; Rio de Janeiro/RJ | C8: Não identificado | F8: https://www.jkesteticaavancada.com.br/ | G8: Pesquisa pública | H8: Prospectar | I8: Site elaborado e amplo catálogo; avaliar integração da consulta com acompanhamento e painel antes de propor substituição. | L8: Identificar gestor/proprietário brasileiro e confirmar canal para proposta comercial. | M8: A confirmar | R8: contato@jkesteticaavancada.com.br é divulgado como Ouvidoria; não foi tratado como endereço de vendas. | S8: Sem data | T8: Formulário | U8: Formulário de consulta no site | V8: https://www.jkesteticaavancada.com.br/ | W8: https://www.jkesteticaavancada.com.br/ | X8: 46302 | Y8: Verificado | Z8: 5 | AA8: 8 | AB8: Site elaborado e amplo catálogo; avaliar integração da consulta com acompanhamento e painel antes de propor substituição. | AC8: Endereços em SP e RJ, serviços e tecnologias variados divulgados; orçamento não foi informado. | AD8: Pendente | AE8: Brasil | AF8: Não identificado | AG8: Não confirmado | AI8: Brasil | AJ8: Média | AK8: Pendente | AL8: Confirmar proprietário/origem brasileira
A9: Clinic Aesthetica Group | B9: São Paulo/SP | C9: Alline Ortiz (proprietária/CEO) | D9: +55 11 97346-9977 | E9: atendimento@clinicspa.com.br | F9: https://www.clinicspa.com.br/ | G9: Pesquisa pública | H9: Prospectar | I9: Já existe calendário/formulário de avaliação no site. Oferecer integração e área do cliente somente se faltar no processo atual. | L9: Confirmar proprietária brasileira e descobrir quais sistemas já utilizam. | M9: A confirmar | R9: Não apresentar como clínica com agendamento apenas por WhatsApp; atendimento@clinicspa.com.br. | S9: Sem data | T9: WhatsApp | U9: +55 11 97346-9977 | V9: https://www.clinicspa.com.br/ | W9: https://www.clinicspa.com.br/ | X9: 46302 | Y9: Verificado | Z9: 4 | AA9: 7 | AB9: Já existe calendário/formulário de avaliação no site. Oferecer integração e área do cliente somente se faltar no processo atual. | AC9: Site anuncia 12 anos de atuação, equipe e linhas de tratamento; sinais de operação estruturada. | AD9: Pendente | AE9: Brasil | AF9: Alline Ortiz (proprietária/CEO) | AG9: Não confirmado | AH9: https://www.clinicspa.com.br/ | AI9: Brasil | AJ9: Média | AK9: Pendente | AL9: Confirmar proprietário/origem brasileira
A10: Derma Mais | B10: Londrina/PR | C10: Marina Mouco Valotto (razão social; vínculo societário a confirmar) | D10: +55 43 99162-2868 | F10: https://clinicaesteticalondrina.com.br/ | G10: Pesquisa pública | H10: Prospectar | I10: Site direciona conversa após coleta de nome e telefone; acompanhamento capilar/facial combina com área privada do cliente. | L10: Confirmar sócios brasileiros e avaliar solicitação de consulta com aprovação da equipe. | M10: A confirmar | R10: CNPJ 31.219.709/0001-06. Liderança técnica não foi automaticamente considerada propriedade. | S10: Sem data | T10: WhatsApp | U10: +55 43 99162-2868 | V10: https://clinicaesteticalondrina.com.br/ | W10: https://clinicaesteticalondrina.com.br/quem-somos/ | X10: 46302 | Y10: Verificado | Z10: 7 | AA10: 7 | AB10: Site direciona conversa após coleta de nome e telefone; acompanhamento capilar/facial combina com área privada do cliente. | AC10: Equipe clínica, financeira e relacionamento identificada; tratamentos capilares/faciais/corporais e unidade física. | AD10: Pendente | AE10: Brasil | AF10: Marina Mouco Valotto (razão social; vínculo societário a confirmar) | AG10: Não confirmado | AH10: https://clinicaesteticalondrina.com.br/quem-somos/ | AI10: Brasil | AJ10: Média | AK10: Pendente | AL10: Confirmar proprietário/origem brasileira
A11: Pró-Corpo | B11: Rede em SP, RJ e PR | C11: Não identificado | D11: +55 11 4118-9955 | F11: https://www.procorpoestetica.com.br/ | G11: Pesquisa pública | H11: Prospectar | I11: Já possui comércio eletrônico e formulário de solicitação de agendamento. Venda simples de site tem baixa aderência; investigar integração. | L11: Confirmar proprietário brasileiro e acesso ao decisor; priorizar depois das clínicas independentes. | M11: A confirmar | R11: Capacidade estimada alta não significa maior facilidade de venda. | S11: Sem data | T11: WhatsApp | U11: +55 11 4118-9955 | V11: https://www.procorpoestetica.com.br/ | W11: https://www.procorpoestetica.com.br/ | X11: 46302 | Y11: Verificado | Z11: 3 | AA11: 9 | AB11: Já possui comércio eletrônico e formulário de solicitação de agendamento. Venda simples de site tem baixa aderência; investigar integração. | AC11: Rede de unidades, catálogo amplo, preços e comércio eletrônico publicados; contratação provavelmente exige avaliação corporativa. | AD11: Pendente | AE11: Brasil | AF11: Não identificado | AG11: Não confirmado | AI11: Brasil | AJ11: Média | AK11: Pendente | AL11: Confirmar proprietário/origem brasileira
A12: VitaSmile | B12: Londres | C12: Não identificado | D12: +44 7848 958312 | F12: https://www.vitasmile.co.uk/ | G12: Pesquisa pública | H12: Prospectar | I12: Clínica odontológica também oferece rejuvenescimento facial; integração de atendimento pode ser útil, mas demanda difere de estética pura. | L12: Confirmar se o proprietário é brasileiro e se há interesse específico na frente de estética. | M12: A confirmar | R12: FORA DO BRASIL. “Clínica brasileira” e atendimento em português não comprovam nacionalidade do dono. | S12: Sem data | T12: WhatsApp | U12: +44 7848 958312 | V12: https://www.vitasmile.co.uk/ | W12: https://www.vitasmile.co.uk/estetica-que-respeita-voce/ | X12: 46302 | Y12: Verificado | Z12: 5 | AA12: 7 | AB12: Clínica odontológica também oferece rejuvenescimento facial; integração de atendimento pode ser útil, mas demanda difere de estética pura. | AC12: Equipe, serviços odontológicos e estética facial, site com preços/financiamento publicados. | AD12: Pendente | AE12: Reino Unido | AF12: Não identificado | AG12: Não confirmado | AI12: FORA DO BRASIL | AJ12: Média | AK12: Pendente | AL12: Confirmar proprietário/origem brasileira
A13: Maison B | B13: Lisboa | C13: Anni Frota | G13: Pesquisa pública | H13: Prospectar | I13: Espaço de estética com tratamentos naturais e quatro salas descrito em reportagem; site e agenda atuais não verificados. | L13: Revalidar funcionamento, telefone e proprietária antes de qualquer abordagem. | M13: A confirmar | R13: FORA DO BRASIL. Reportagem de 22/12/2022. Não presumir que telefone aceita WhatsApp nem que contato continua ativo. | S13: Sem data | T13: Telefone | U13: +351 912 349 066 | W13: https://www.nit.pt/compras/maison-b-o-novo-espaco-de-beleza-em-lisboa-onde-todos-os-tratamentos-sao-naturais | X13: 46302 | Y13: Pendente | Z13: 6 | AA13: 6 | AB13: Espaço de estética com tratamentos naturais e quatro salas descrito em reportagem; site e agenda atuais não verificados. | AC13: Estrutura de quatro salas e serviços publicados em 2022. Evidência histórica, sem validação financeira atual. | AD13: Pendente | AE13: Portugal | AF13: Anni Frota | AG13: Brasileira explícita em fonte | AH13: https://www.nit.pt/compras/maison-b-o-novo-espaco-de-beleza-em-lisboa-onde-todos-os-tratamentos-sao-naturais | AI13: FORA DO BRASIL | AJ13: Baixa | AK13: Pendente | AL13: Revalidar contato/atividade atual
A14: Bellavish Aesthetic Clinic | B14: Dublin | C14: Phamela Priscila Bezerra | G14: Pesquisa pública | H14: Prospectar | I14: Clínica de estética descrita em matéria institucional; jornada digital atual não pôde ser validada. | L14: Revalidar atividade e telefone; confirmar responsável atual. | M14: A confirmar | R14: FORA DO BRASIL. Fonte de 21/09/2022: nasceu em Londrina/PR. E-mail ofuscado não foi inventado. Domínio antigo não foi considerado site atual. | S14: Sem data | T14: Telefone | U14: +353 89 607 6938 | W14: https://nepuga.edu.br/news/biomedica-esteta-europa/ | X14: 46302 | Y14: Pendente | Z14: 6 | AA14: 6 | AB14: Clínica de estética descrita em matéria institucional; jornada digital atual não pôde ser validada. | AC14: Experiência e operação clínica descritas em 2022; sinal histórico insuficiente para inferir orçamento atual. | AD14: Pendente | AE14: Irlanda | AF14: Phamela Priscila Bezerra | AG14: Origem brasileira documentada | AH14: https://nepuga.edu.br/news/biomedica-esteta-europa/ | AI14: FORA DO BRASIL | AJ14: Baixa | AK14: Pendente | AL14: Revalidar contato/atividade atual
A15: Brazilicious Beauty Spa | B15: Austin/Texas (referência histórica) | C15: Josie Rushing | F15: https://braziliciousbeautyspa.com/ | G15: Pesquisa pública | H15: Prospectar | I15: Proprietária brasileira identificada em reportagem; contato comercial atual e experiência do site não puderam ser verificados. | L15: Localizar fonte atual de contato comercial; manter fora da fila de abordagem. | M15: A confirmar | R15: FORA DO BRASIL. Reportagem de 29/04/2022; site bloqueou acesso automatizado. brazilicious.com é comércio de pão de queijo e não pertence a este registro. | S15: Sem data | X15: 46302 | Y15: Pendente | AB15: Proprietária brasileira identificada em reportagem; contato comercial atual e experiência do site não puderam ser verificados. | AC15: Não pontuado: faturamento histórico de reportagem não comprova orçamento atual. | AD15: Pendente | AE15: Estados Unidos | AF15: Josie Rushing | AG15: Brasileira explícita em fonte | AH15: https://revistapegn.globo.com/Mulheres-empreendedoras/noticia/2022/04/brasileira-fatura-r-2-milhoes-com-drenagem-linfatica-nos-eua.html | AI15: FORA DO BRASIL | AJ15: Não atribuída | AK15: Pendente | AL15: Localizar contato comercial atual fora do Instagram

Sheet Resumo
A1: Indicador | B1: Valor
A2: Candidatos pesquisados | B2: =COUNTA(CRM!A5:A204) -> 13
A3: Qualificados na pesquisa | B3: =COUNTIF(CRM!AK5:AK204,"Qualificado") -> 2
A4: Pendentes de qualificação | B4: =COUNTIF(CRM!AK5:AK204,"Pendente") -> 11
A5: Fora do Brasil | B5: =COUNTIF(CRM!AI5:AI204,"FORA DO BRASIL") -> 4
A6: Contratos fechados | B6: =COUNTIF(CRM!H5:H204,"Fechado") -> 0
A7: Retornos hoje | B7: =COUNTIF(CRM!S5:S204,"Hoje") -> 0
A8: Retornos atrasados | B8: =COUNTIF(CRM!S5:S204,"Atrasado") -> 0
A11: Nenhuma mensagem foi enviada. Telefones publicados não foram testados por ligação.

Sheet Como usar
A1: Tema | B1: Orientação
A2: Comece aqui | B2: Edite a aba CRM. Qualificados e Pendentes são cópias da fotografia inicial, não se sincronizam com suas edições. Filtre Qualificação e Próxima ação.
A3: Proprietário brasileiro | B3: Aceitamos menção explícita a brasileiro(a) ou biografia que identifique cidade natal no Brasil. Origem documentada não equivale a verificação jurídica de cidadania. Nome português, endereço brasileiro e formação no Brasil não bastam.
A4: Contatos | B4: São contatos públicos da empresa, não dados privados. Publicado/verificado significa visto na fonte, não telefone testado nem autorização para receber propaganda.
A5: Revalidar antigos | B5: Maison B e Bellavish: reportagem de 2022. Brazilicious: proprietário em matéria de 2022, contato atual não localizado. Não estão na fila qualificada.
A6: Planilha operacional | B6: Preencha etapa, último contato, próximo contato, próxima ação e propostas. As colunas Situação retorno e Prioridade contêm fórmulas. Há 200 posições.
A7: Qualificar manualmente | B7: Após confirmar dono/origem e contato recente com fonte, atualize Qualificação, Verificação e pendências. Não transforme hipótese em fato. Notas podem ser revistas com descobertas novas.
A8: Orçamento | B8: Capacidade 0–10 é uma estimativa comercial ordinal baseada em estrutura visível. Não revela faturamento, caixa, verba ou aceitação do preço. Propostas ficaram em branco.
A9: Instagram | B9: Instagram não é canal principal. Sem outro contato verificável, o registro fica fora da fila de abordagem; contatos comprovadamente apenas Instagram devem ser descartados.
A10: Mensagens | B10: Comece com apresentação individual, contexto do site e pedido de permissão para enviar demonstração. Respeite recusa e evite disparos em massa.
A11: Escopo | B11: Levantamento inicial de 13 candidatos, não estudo censitário nem garantia de vendas. Consulta pública em 07/10/2026; fontes antigas identificadas explicitamente.

Sheet Critérios das notas
A1: Dimensão | B1: Faixas / método | C1: Aplicação
A2: Potencial 0–10 | B2: 0–2: pouca aderência; 3–4: sistema/site já maduro; 5–6: oportunidade depende de integração; 7–8: lacuna visível na jornada e boa aderência; 9–10: necessidade validada diretamente. | C2: Avaliação ordinal da aderência ao nosso produto, jornada de agendamento, acompanhamento e facilidade de chegar ao decisor. Sem entrevistas não atribuímos 9–10.
A3: Capacidade estimada 0–10 | B3: 0–2: estrutura limitada comprovada; 3–4: operação pequena; 5–6: unidade/serviços com estrutura publicada; 7–8: equipe/unidades/tecnologias; 9–10: operação de rede/grupo claramente documentada. | C3: Sinais: unidades, equipe, variedade/tecnologia, maturidade digital e posicionamento/estrutura física publicados. Não é pontuação de renda pessoal. Ausência de evidência não vira zero.
A4: Confiança | B4: Média: sinais publicados em páginas oficiais atuais; Baixa: informação antiga ou parcial; Não atribuída: insuficiente. | C4: Todas as notas podem estar erradas; validar orçamento e processo de compra em conversa com a empresa.
A5: Prioridade | B5: Alta: potencial ≥7 e capacidade ≥6; Média: potencial ≥5 e capacidade ≥4; Baixa: demais qualificados. | C5: Qualificação pendente, contato não verificado ou notas ausentes prevalecem e produzem Pendente.
A6: Limite da análise de sites | B6: Observamos páginas públicas, links e formulários. Não entramos em áreas autenticadas nem testamos envio de consultas. | C6: Formulário visível não prova funcionamento interno. WhatsApp no site não prova ausência de CRM ou sistema de agenda.

Sheet Mapa do segmento
A1: Segmento / assunto | B1: Dor a investigar | C1: Oferta / recomendação
A2: Clínica independente de estética | B2: Atendimento manual, informações desatualizadas, solicitações dispersas e retorno de clientes. | C2: Site editável + solicitações com aprovação + cadastro + área do cliente. Melhor hipótese de entrada para piloto, confirmar na conversa.
A3: Dermatologia / clínica médica | B3: Agenda por profissional, reputação, publicidade e coordenação da recepção. | C3: Apresentar ganho no fluxo de atendimento e integração; aplicar regras do CFM e identificação profissional conforme o tipo de serviço.
A4: Redes / franquias | B4: Autonomia local versus compras centralizadas, múltiplas unidades e sistemas já contratados. | C4: Oferta de piloto por unidade ou integração. Ciclo comercial provavelmente mais longo; não pressupor verba disponível.
A5: Spa / bem-estar | B5: Recorrência, protocolos, acompanhamento e disponibilidade da equipe. | C5: Solicitações de consulta, histórico de atendimento e conteúdo atualizado; confirmar limites e preferências do serviço.
A6: Brasileiros no exterior | B6: Idioma, fuso horário, moeda, operação local e regras do país. | C6: Site bilíngue e horários locais são possíveis extensões, não funcionalidades já garantidas. Verificar legislação e contratação local.
A7: Posicionamento | B7: Um site bonito pode já existir; substituir só pelo visual é uma proposta fraca. | C7: Demonstrar a passagem do cadastro à solicitação, aprovação e manutenção do catálogo. Não prometer faturamento ou eliminar faltas.
A8: Preço para testar | B8: Oferta comercial do fornecedor é distinta da capacidade estimada do cliente. | C8: Hipótese inicial: implantação R$3.490 + R$397/mês, com escopo fechado. Domínio, serviços pagos, integrações e suporte extra devem ser definidos. Para exterior, cotar depois de conhecer escopo/moeda.
A9: Descoberta comercial | B9: Volume de solicitações, faltas, tempo de resposta, quem edita o site, sistema atual, decisor e verba. | C9: Perguntar por números reais. Medir no piloto: conversão em solicitações válidas, tempo de resposta e aprovação; não inferir resultados só do site.
A10: Mercado e estatística | B10: Não confundir procedimentos médicos realizados por cirurgiões plásticos com o universo de clínicas de estética. | C10: ISAPS tem pesquisa anual restrita a esse escopo. Nenhum tamanho de mercado ou faturamento setorial foi inventado neste estudo.
A11: Galeria / acompanhamento | B11: Fotos públicas e evolução privada exigem finalidade e autorização adequadas. | C11: Separar galeria pública aprovada de área do paciente, revisar permissões e acesso; regras variam por profissional e local.

Sheet Fontes
A1: Clínica / tema | B1: Fonte consultada | C1: O que comprova / limite
A2: Instituto Remodele | B2: https://remodele.com.br/assets/index-ClmuxGc9.js | C2: CNPJ 63.154.444/0001-00; contato@remodele.com.br. Não confundir com Instituto Remodele de Rio Preto. Consulta em 07/10/2026.
A3: Art Beauty Center | B3: https://www.artbeautycenter.com.br/sobre-nos https://www.artbeautycenter.com.br/sobre-nos | C3: WhatsApp de agendamento de São Paulo. Há divergência em outros telefones do rodapé; não foram usados. Consulta em 07/10/2026.
A4: Danielle Oliveira Estética Avançada | B4: https://www.danielleoliveira.com.br/ https://www.danielleoliveira.com.br/ | C4: Contato da unidade Limão; contato@danielleoliveira.com.br. Formação no Brasil não comprova nacionalidade. Consulta em 07/10/2026.
A5: JK Estética Avançada | B5: https://www.jkesteticaavancada.com.br/ | C5: contato@jkesteticaavancada.com.br é divulgado como Ouvidoria; não foi tratado como endereço de vendas. Consulta em 07/10/2026.
A6: Clinic Aesthetica Group | B6: https://www.clinicspa.com.br/ https://www.clinicspa.com.br/ | C6: Não apresentar como clínica com agendamento apenas por WhatsApp; atendimento@clinicspa.com.br. Consulta em 07/10/2026.
A7: Derma Mais | B7: https://clinicaesteticalondrina.com.br/quem-somos/ https://clinicaesteticalondrina.com.br/quem-somos/ | C7: CNPJ 31.219.709/0001-06. Liderança técnica não foi automaticamente considerada propriedade. Consulta em 07/10/2026.
A8: Pró-Corpo | B8: https://www.procorpoestetica.com.br/ | C8: Capacidade estimada alta não significa maior facilidade de venda. Consulta em 07/10/2026.
A9: Natalia Beauty Clinic | B9: https://nataliabeauty.com.br/clinica/ https://nataliabeauty.com.br/quem-somos/ | C9: Biografia oficial: “Natural da capital de São Paulo”. Origem brasileira documentada, sem verificação de documentos de cidadania. Não usar WhatsApp da agência no rodapé. Consulta em 07/10/2026.
A10: SPA Renata França | B10: https://www.sparenatafranca.com/nossa-historia/renata https://www.sparenatafranca.com/nossa-historia/renata | C10: Biografia oficial identifica Ilhéus/BA como cidade natal (“hometown”). Origem brasileira documentada, cidadania legal não verificada. Não usar números de cursos ou venda corporativa. Consulta em 07/10/2026.
A11: VitaSmile | B11: https://www.vitasmile.co.uk/estetica-que-respeita-voce/ | C11: FORA DO BRASIL. “Clínica brasileira” e atendimento em português não comprovam nacionalidade do dono. Consulta em 07/10/2026.
A12: Maison B | B12: https://www.nit.pt/compras/maison-b-o-novo-espaco-de-beleza-em-lisboa-onde-todos-os-tratamentos-sao-naturais https://www.nit.pt/compras/maison-b-o-novo-espaco-de-beleza-em-lisboa-onde-todos-os-tratamentos-sao-naturais | C12: FORA DO BRASIL. Reportagem de 22/12/2022. Não presumir que telefone aceita WhatsApp nem que contato continua ativo. Consulta em 07/10/2026.
... A16: Publicidade médica CFM | B16: https://publicidademedica.cfm.org.br/ | C16: Guia da Resolução CFM 2.336/2023. Identificação, divulgação e condições para fotos; aplicação a médicos. Consulta 07/10/2026.

Sheet Descartados
A1: Registro | B1: Motivo | C1: Fonte
A2: Studio E.F. Training & Beauty | B2: Site atual apresenta escola de formação, fora do escopo desta lista de clínicas. Fundadora brasileira confirmada, mas isso não resolve a diferença de atividade. | C2: https://training-beauty.com/
A3: brazilicious.com | B3: Loja de pão de queijo, não Brazilicious Beauty Spa. Domínio semelhante não identifica a empresa correta. | C3: https://brazilicious.com/
A4: tonyabeauty.com | B4: Site de Tonya Wilson / salão em Dallas; não identifica Tonya Silva Pereira da clínica citada em reportagem. Não usar como contato da clínica. | C4: https://tonyabeauty.com/
