Workbook
Name Etapas: Listas!$A$1:$A$9
Name Motivos: Listas!$D$1:$D$6
Name Origens: Listas!$B$1:$B$8
Name Preferencias: Listas!$C$1:$C$3
Name Proprietarios: 'Listas'!$F$1:$F$3

Sheet Comece aqui
B2: Seu CRM de vendas para clínicas
B4: Registre os contatos na aba CRM. A aba Resumo acompanha o funil e os próximos retornos. Os exemplos fictícios ficam separados e não entram nos indicadores.
B7: 1 · Cadastre a clínica
B8: Preencha clínica, cidade, responsável e o canal comercial divulgado. Escreva uma observação concreta sobre o negócio.
B11: 2 · Atualize a etapa
B12: Use a lista da coluna Etapa conforme a conversa avança. Registre cada contato e o próximo passo.
B15: 3 · Agende o retorno
B16: Informe Próximo contato e Próxima ação. Situação do retorno sinaliza atrasos e contatos previstos para hoje.
B19: 4 · Respeite a preferência
B20: Selecione Não contatar quando houver recusa. Isso prevalece sobre o alerta de retorno. A planilha não envia mensagens.
B23: 5 · Registre a proposta
B24: Informe implantação e mensalidade em suas colunas. Ao fechar, marque Fechado e preencha Data do fechamento.
... B39: PROSPECÇÃO QUALIFICADA: colunas T–AI registram canais, fontes, notas, proprietário e país. O Instituto Remodele está pendente, informado pelo usuário, sem novos contatos verificados. Excluir contato apenas via Instagram e proprietário não brasileiro; destacar clínicas fora do Brasil. Consulte Critérios das notas e Mapa do segmento.

Sheet CRM
A1: CRM · Prospecção e acompanhamento | T1: QUALIFICAÇÃO · FONTES · PRIORIDADE
A2: Preencha as células em azul. Use os filtros para selecionar etapa, origem e retornos pendentes. Não substitua as fórmulas da última coluna. | T2: Somente canais comerciais fora do Instagram. Notas exigem evidências; sem dados suficientes, mantenha em branco.
A4: Clínica | B4: Cidade / UF | C4: Responsável | D4: WhatsApp comercial | E4: E-mail comercial | F4: Instagram / site | G4: Origem | H4: Etapa | I4: Interesse / necessidade | J4: Último contato | K4: Próximo contato | L4: Próxima ação | M4: Preferência de contato | N4: Implantação proposta (R$) | O4: Mensalidade proposta (R$) | P4: Data do fechamento | Q4: Motivo da perda | R4: Observações | S4: Situação do retorno | T4: Canal principal | U4: Contato principal | V4: Site verificado | W4: Fonte pública do contato | X4: Data de verificação | Y4: Verificação | Z4: Potencial comercial (0–10) | AA4: Capacidade estimada (0–10) | AB4: Evidências do potencial | AC4: Evidências da capacidade | AD4: Prioridade comercial | AE4: País da clínica | AF4: Proprietário identificado | AG4: Proprietário brasileiro? | AH4: Fonte sobre proprietário / nacionalidade | AI4: Localização internacional
A5: Instituto Remodele | G5: Outro | H5: Prospectar | I5: Site simples; agendamento pelo WhatsApp, segundo o usuário. | L5: Verificar site oficial e canal comercial; identificar o responsável pela contratação. | M5: A confirmar | R5: Origem: relato do usuário nesta conversa. Cidade, site e contato ainda não confirmados. | S5: =IF(A5="","",IF(M5="Não contatar","Não contatar",IF(OR(H5="Fechado",H5="Perdido"),"Encerrado",IF(K5="","Sem data",IF(K5<TODAY(),"Atrasado",IF(K5=TODAY(),"Hoje","Agendado"))))))) | T5: WhatsApp | Y5: Pendente | AB5: Informação preliminar do usuário. Pontuação depende de validação. | AC5: Sem evidências públicas verificadas; nota não atribuída. | AD5: =IF(A5="","",IF(OR(Y5="Descartado",M5="Não contatar",T5="Instagram",AG5="Não"),"Descartar",IF(OR(Y5<>"Verificado",U5="",W5="",X5="",Z5="",AA5="",AE5="",AF5="",AG5<>"Sim, confirmado",AH5=""),"Pendente",IF(AND(Z5>=7,AA5>=6),"Alta",IF(AND(Z5>=5,AA5>=4),"Média","Baixa"))))) | AG5: Não confirmado | AI5: =IF(A5="","",IF(AE5="","País a verificar",IF(AE5="Brasil","Brasil","FORA DO BRASIL · "&AE5)))
S6: =IF(A6="","",IF(M6="Não contatar","Não contatar",IF(OR(H6="Fechado",H6="Perdido"),"Encerrado",IF(K6="","Sem data",IF(K6<TODAY(),"Atrasado",IF(K6=TODAY(),"Hoje","Agendado"))))))) | AD6: =IF(A6="","",IF(OR(Y6="Descartado",M6="Não contatar",T6="Instagram",AG6="Não"),"Descartar",IF(OR(Y6<>"Verificado",U6="",W6="",X6="",Z6="",AA6="",AE6="",AF6="",AG6<>"Sim, confirmado",AH6=""),"Pendente",IF(AND(Z6>=7,AA6>=6),"Alta",IF(AND(Z6>=5,AA6>=4),"Média","Baixa"))))) | AI6: =IF(A6="","",IF(AE6="","País a verificar",IF(AE6="Brasil","Brasil","FORA DO BRASIL · "&AE6)))
S7: =IF(A7="","",IF(M7="Não contatar","Não contatar",IF(OR(H7="Fechado",H7="Perdido"),"Encerrado",IF(K7="","Sem data",IF(K7<TODAY(),"Atrasado",IF(K7=TODAY(),"Hoje","Agendado"))))))) | AD7: =IF(A7="","",IF(OR(Y7="Descartado",M7="Não contatar",T7="Instagram",AG7="Não"),"Descartar",IF(OR(Y7<>"Verificado",U7="",W7="",X7="",Z7="",AA7="",AE7="",AF7="",AG7<>"Sim, confirmado",AH7=""),"Pendente",IF(AND(Z7>=7,AA7>=6),"Alta",IF(AND(Z7>=5,AA7>=4),"Média","Baixa"))))) | AI7: =IF(A7="","",IF(AE7="","País a verificar",IF(AE7="Brasil","Brasil","FORA DO BRASIL · "&AE7)))
S8: =IF(A8="","",IF(M8="Não contatar","Não contatar",IF(OR(H8="Fechado",H8="Perdido"),"Encerrado",IF(K8="","Sem data",IF(K8<TODAY(),"Atrasado",IF(K8=TODAY(),"Hoje","Agendado"))))))) | AD8: =IF(A8="","",IF(OR(Y8="Descartado",M8="Não contatar",T8="Instagram",AG8="Não"),"Descartar",IF(OR(Y8<>"Verificado",U8="",W8="",X8="",Z8="",AA8="",AE8="",AF8="",AG8<>"Sim, confirmado",AH8=""),"Pendente",IF(AND(Z8>=7,AA8>=6),"Alta",IF(AND(Z8>=5,AA8>=4),"Média","Baixa"))))) | AI8: =IF(A8="","",IF(AE8="","País a verificar",IF(AE8="Brasil","Brasil","FORA DO BRASIL · "&AE8)))
S9: =IF(A9="","",IF(M9="Não contatar","Não contatar",IF(OR(H9="Fechado",H9="Perdido"),"Encerrado",IF(K9="","Sem data",IF(K9<TODAY(),"Atrasado",IF(K9=TODAY(),"Hoje","Agendado"))))))) | AD9: =IF(A9="","",IF(OR(Y9="Descartado",M9="Não contatar",T9="Instagram",AG9="Não"),"Descartar",IF(OR(Y9<>"Verificado",U9="",W9="",X9="",Z9="",AA9="",AE9="",AF9="",AG9<>"Sim, confirmado",AH9=""),"Pendente",IF(AND(Z9>=7,AA9>=6),"Alta",IF(AND(Z9>=5,AA9>=4),"Média","Baixa"))))) | AI9: =IF(A9="","",IF(AE9="","País a verificar",IF(AE9="Brasil","Brasil","FORA DO BRASIL · "&AE9)))
S10: =IF(A10="","",IF(M10="Não contatar","Não contatar",IF(OR(H10="Fechado",H10="Perdido"),"Encerrado",IF(K10="","Sem data",IF(K10<TODAY(),"Atrasado",IF(K10=TODAY(),"Hoje","Agendado"))))))) | AD10: =IF(A10="","",IF(OR(Y10="Descartado",M10="Não contatar",T10="Instagram",AG10="Não"),"Descartar",IF(OR(Y10<>"Verificado",U10="",W10="",X10="",Z10="",AA10="",AE10="",AF10="",AG10<>"Sim, confirmado",AH10=""),"Pendente",IF(AND(Z10>=7,AA10>=6),"Alta",IF(AND(Z10>=5,AA10>=4),"Média","Baixa"))))) | AI10: =IF(A10="","",IF(AE10="","País a verificar",IF(AE10="Brasil","Brasil","FORA DO BRASIL · "&AE10)))
S11: =IF(A11="","",IF(M11="Não contatar","Não contatar",IF(OR(H11="Fechado",H11="Perdido"),"Encerrado",IF(K11="","Sem data",IF(K11<TODAY(),"Atrasado",IF(K11=TODAY(),"Hoje","Agendado"))))))) | AD11: =IF(A11="","",IF(OR(Y11="Descartado",M11="Não contatar",T11="Instagram",AG11="Não"),"Descartar",IF(OR(Y11<>"Verificado",U11="",W11="",X11="",Z11="",AA11="",AE11="",AF11="",AG11<>"Sim, confirmado",AH11=""),"Pendente",IF(AND(Z11>=7,AA11>=6),"Alta",IF(AND(Z11>=5,AA11>=4),"Média","Baixa"))))) | AI11: =IF(A11="","",IF(AE11="","País a verificar",IF(AE11="Brasil","Brasil","FORA DO BRASIL · "&AE11)))
S12: =IF(A12="","",IF(M12="Não contatar","Não contatar",IF(OR(H12="Fechado",H12="Perdido"),"Encerrado",IF(K12="","Sem data",IF(K12<TODAY(),"Atrasado",IF(K12=TODAY(),"Hoje","Agendado"))))))) | AD12: =IF(A12="","",IF(OR(Y12="Descartado",M12="Não contatar",T12="Instagram",AG12="Não"),"Descartar",IF(OR(Y12<>"Verificado",U12="",W12="",X12="",Z12="",AA12="",AE12="",AF12="",AG12<>"Sim, confirmado",AH12=""),"Pendente",IF(AND(Z12>=7,AA12>=6),"Alta",IF(AND(Z12>=5,AA12>=4),"Média","Baixa"))))) | AI12: =IF(A12="","",IF(AE12="","País a verificar",IF(AE12="Brasil","Brasil","FORA DO BRASIL · "&AE12)))
S13: =IF(A13="","",IF(M13="Não contatar","Não contatar",IF(OR(H13="Fechado",H13="Perdido"),"Encerrado",IF(K13="","Sem data",IF(K13<TODAY(),"Atrasado",IF(K13=TODAY(),"Hoje","Agendado"))))))) | AD13: =IF(A13="","",IF(OR(Y13="Descartado",M13="Não contatar",T13="Instagram",AG13="Não"),"Descartar",IF(OR(Y13<>"Verificado",U13="",W13="",X13="",Z13="",AA13="",AE13="",AF13="",AG13<>"Sim, confirmado",AH13=""),"Pendente",IF(AND(Z13>=7,AA13>=6),"Alta",IF(AND(Z13>=5,AA13>=4),"Média","Baixa"))))) | AI13: =IF(A13="","",IF(AE13="","País a verificar",IF(AE13="Brasil","Brasil","FORA DO BRASIL · "&AE13)))
S14: =IF(A14="","",IF(M14="Não contatar","Não contatar",IF(OR(H14="Fechado",H14="Perdido"),"Encerrado",IF(K14="","Sem data",IF(K14<TODAY(),"Atrasado",IF(K14=TODAY(),"Hoje","Agendado"))))))) | AD14: =IF(A14="","",IF(OR(Y14="Descartado",M14="Não contatar",T14="Instagram",AG14="Não"),"Descartar",IF(OR(Y14<>"Verificado",U14="",W14="",X14="",Z14="",AA14="",AE14="",AF14="",AG14<>"Sim, confirmado",AH14=""),"Pendente",IF(AND(Z14>=7,AA14>=6),"Alta",IF(AND(Z14>=5,AA14>=4),"Média","Baixa"))))) | AI14: =IF(A14="","",IF(AE14="","País a verificar",IF(AE14="Brasil","Brasil","FORA DO BRASIL · "&AE14)))
S15: =IF(A15="","",IF(M15="Não contatar","Não contatar",IF(OR(H15="Fechado",H15="Perdido"),"Encerrado",IF(K15="","Sem data",IF(K15<TODAY(),"Atrasado",IF(K15=TODAY(),"Hoje","Agendado"))))))) | AD15: =IF(A15="","",IF(OR(Y15="Descartado",M15="Não contatar",T15="Instagram",AG15="Não"),"Descartar",IF(OR(Y15<>"Verificado",U15="",W15="",X15="",Z15="",AA15="",AE15="",AF15="",AG15<>"Sim, confirmado",AH15=""),"Pendente",IF(AND(Z15>=7,AA15>=6),"Alta",IF(AND(Z15>=5,AA15>=4),"Média","Baixa"))))) | AI15: =IF(A15="","",IF(AE15="","País a verificar",IF(AE15="Brasil","Brasil","FORA DO BRASIL · "&AE15)))
S16: =IF(A16="","",IF(M16="Não contatar","Não contatar",IF(OR(H16="Fechado",H16="Perdido"),"Encerrado",IF(K16="","Sem data",IF(K16<TODAY(),"Atrasado",IF(K16=TODAY(),"Hoje","Agendado"))))))) | AD16: =IF(A16="","",IF(OR(Y16="Descartado",M16="Não contatar",T16="Instagram",AG16="Não"),"Descartar",IF(OR(Y16<>"Verificado",U16="",W16="",X16="",Z16="",AA16="",AE16="",AF16="",AG16<>"Sim, confirmado",AH16=""),"Pendente",IF(AND(Z16>=7,AA16>=6),"Alta",IF(AND(Z16>=5,AA16>=4),"Média","Baixa"))))) | AI16: =IF(A16="","",IF(AE16="","País a verificar",IF(AE16="Brasil","Brasil","FORA DO BRASIL · "&AE16)))
S17: =IF(A17="","",IF(M17="Não contatar","Não contatar",IF(OR(H17="Fechado",H17="Perdido"),"Encerrado",IF(K17="","Sem data",IF(K17<TODAY(),"Atrasado",IF(K17=TODAY(),"Hoje","Agendado"))))))) | AD17: =IF(A17="","",IF(OR(Y17="Descartado",M17="Não contatar",T17="Instagram",AG17="Não"),"Descartar",IF(OR(Y17<>"Verificado",U17="",W17="",X17="",Z17="",AA17="",AE17="",AF17="",AG17<>"Sim, confirmado",AH17=""),"Pendente",IF(AND(Z17>=7,AA17>=6),"Alta",IF(AND(Z17>=5,AA17>=4),"Média","Baixa"))))) | AI17: =IF(A17="","",IF(AE17="","País a verificar",IF(AE17="Brasil","Brasil","FORA DO BRASIL · "&AE17)))
... S204: =IF(A204="","",IF(M204="Não contatar","Não contatar",IF(OR(H204="Fechado",H204="Perdido"),"Encerrado",IF(K204="","Sem data",IF(K204<TODAY(),"Atrasado",IF(K204=TODAY(),"Hoje","Agendado"))))))) | AD204: =IF(A204="","",IF(OR(Y204="Descartado",M204="Não contatar",T204="Instagram",AG204="Não"),"Descartar",IF(OR(Y204<>"Verificado",U204="",W204="",X204="",Z204="",AA204="",AE204="",AF204="",AG204<>"Sim, confirmado",AH204=""),"Pendente",IF(AND(Z204>=7,AA204>=6),"Alta",IF(AND(Z204>=5,AA204>=4),"Média","Baixa"))))) | AI204: =IF(A204="","",IF(AE204="","País a verificar",IF(AE204="Brasil","Brasil","FORA DO BRASIL · "&AE204)))

Sheet Listas
A1: Prospectar | B1: Google Maps | C1: A confirmar | D1: Sem interesse | F1: Sim, confirmado
A2: Contatado | B2: Instagram | C2: Autorizado | D2: Sem orçamento | F2: Não
A3: Em conversa | B3: Indicação | C3: Não contatar | D3: Já tem solução | F3: Não confirmado
A4: Demonstração marcada | B4: WhatsApp | D4: Sem retorno
A5: Proposta enviada | B5: E-mail | D5: Sem prioridade
A6: Negociação | B6: Anúncio | D6: Outro
A7: Fechado | B7: Evento
A8: Perdido | B8: Outro
A9: Retomar depois

Sheet Resumo
B2: Resumo comercial
B5: Indicadores calculados a partir das clínicas preenchidas na aba CRM.
B7: Clínicas cadastradas | F7: Retornos atrasados | J7: Retornos para hoje
B8: =COUNTA(CRM!A5:A204) | F8: =COUNTIF(CRM!S5:S204,"Atrasado") | J8: =COUNTIF(CRM!S5:S204,"Hoje")
B11: Contratos fechados | F11: Implantação fechada | J11: Mensalidade contratada
B12: =COUNTIFS(CRM!A5:A204,"<>",CRM!H5:H204,"Fechado") | F12: =SUMIFS(CRM!N5:N204,CRM!A5:A204,"<>",CRM!H5:H204,"Fechado") | J12: =SUMIFS(CRM!O5:O204,CRM!A5:A204,"<>",CRM!H5:H204,"Fechado")
B16: Funil por etapa
B17: Etapa | E17: Clínicas
B18: Prospectar | E18: =COUNTIFS(CRM!A5:A204,"<>",CRM!H5:H204,B18)
B19: Contatado | E19: =COUNTIFS(CRM!A5:A204,"<>",CRM!H5:H204,B19)
B20: Em conversa | E20: =COUNTIFS(CRM!A5:A204,"<>",CRM!H5:H204,B20)
B21: Demonstração marcada | E21: =COUNTIFS(CRM!A5:A204,"<>",CRM!H5:H204,B21)
B22: Proposta enviada | E22: =COUNTIFS(CRM!A5:A204,"<>",CRM!H5:H204,B22)
B23: Negociação | E23: =COUNTIFS(CRM!A5:A204,"<>",CRM!H5:H204,B23)
B24: Fechado | E24: =COUNTIFS(CRM!A5:A204,"<>",CRM!H5:H204,B24)
B25: Perdido | E25: =COUNTIFS(CRM!A5:A204,"<>",CRM!H5:H204,B25)
B26: Retomar depois | E26: =COUNTIFS(CRM!A5:A204,"<>",CRM!H5:H204,B26)
B29: Pipeline de propostas (implantação)
B30: =SUMIFS(CRM!N5:N204,CRM!A5:A204,"<>",CRM!H5:H204,"Proposta enviada")+SUMIFS(CRM!N5:N204,CRM!A5:A204,"<>",CRM!H5:H204,"Negociação")
B33: Mensalidade contratada é a soma das propostas marcadas como Fechado; não representa pagamentos recebidos. O pipeline considera implantação das propostas em negociação, sem estimar probabilidade de fechamento. Registre cobranças e recebimentos em um controle financeiro separado.

Sheet Exemplo fictício
A1: Exemplos fictícios · não entram no Resumo
A2: Use estas três linhas como referência de preenchimento. Não são contatos reais. Cadastre suas clínicas somente na aba CRM.
A4: Clínica | B4: Cidade / UF | C4: Responsável | D4: WhatsApp comercial | E4: E-mail comercial | F4: Instagram / site | G4: Origem | H4: Etapa | I4: Interesse / necessidade | J4: Último contato | K4: Próximo contato | L4: Próxima ação | M4: Preferência de contato | N4: Implantação proposta (R$) | O4: Mensalidade proposta (R$) | P4: Data do fechamento | Q4: Motivo da perda | R4: Observações | S4: Situação do retorno
A5: Clínica Aurora · exemplo | B5: São Paulo / SP | C5: Responsável fictício | G5: Instagram | H5: Demonstração marcada | I5: Quer organizar os pedidos do WhatsApp | J5: 46302 | K5: 46303 | L5: Apresentar o fluxo de solicitação e aprovação | M5: Autorizado | N5: 3490 | O5: 397 | R5: Demonstração de 15 minutos | S5: Agendado
A6: Clínica Horizonte · exemplo | B6: Campinas / SP | C6: Responsável fictício | G6: Indicação | H6: Proposta enviada | I6: Precisa atualizar tratamentos e fotos | J6: 46300 | K6: 46302 | L6: Verificar dúvidas sobre a proposta | M6: Autorizado | N6: 3490 | O6: 397 | R6: Combinar prazo após receber o material | S6: Hoje
A7: Clínica Jardim · exemplo | B7: Curitiba / PR | C7: Responsável fictício | G7: Google Maps | H7: Perdido | I7: Sem prioridade neste momento | J7: 46302 | L7: Encerrar os retornos | M7: Não contatar | Q7: Sem prioridade | R7: Respeitar a preferência registrada | S7: Não contatar

Sheet Critérios das notas
A1: COMO QUALIFICAR AS CLÍNICAS | B1: Potencial comercial e capacidade estimada
A2: Limite da estimativa | B2: Capacidade estimada é um indicador de estrutura comercial aparente. Não é renda, faturamento, lucro nem orçamento conhecido. | C2: Sem dados suficientes: deixe a nota vazia. Não use zero para representar desconhecimento.
A3: Filtro obrigatório | B3: Canal comercial público: WhatsApp, telefone, e-mail ou formulário. | C3: Se o único canal for Instagram, descarte. Ter Instagram não desqualifica uma clínica que tenha outro canal comercial verificado.
A4: Verificação | B4: Registre URL da fonte oficial, data da consulta e contato publicado. | C4: Não invente números, e-mails, nomes de responsáveis nem situação do site.
A5: POTENCIAL · soma de 5 critérios | B5: 0, 1 ou 2 pontos por critério; total de 0 a 10. | C5: Atribua a soma somente após investigar os cinco critérios.
A6: 1. Compatibilidade do segmento | B6: 0: fora do escopo; 1: serviços parcialmente aderentes; 2: clínica estética com operação aderente. | C6: Fonte: serviços descritos no site oficial.
A7: 2. Oportunidade no agendamento | B7: 0: fluxo completo já existente; 1: fluxo parcial; 2: somente contato manual para pedir horário. | C7: Não afirmar que não há sistema interno: observar apenas o fluxo público e confirmar em conversa.
A8: 3. Oportunidade no conteúdo | B8: 0: site atende bem à apresentação; 1: melhorias pontuais; 2: falta relevante de organização, conteúdo ou experiência mobile. | C8: Descrever problemas observáveis. Não afirmar autoria por IA pela aparência.
A9: 4. Adequação ao painel | B9: 0: pouca necessidade aparente; 1: alguns serviços/equipe; 2: catálogo ou equipe que se beneficiam da gestão. | C9: Necessidade operacional real deve ser confirmada com a clínica.
A10: 5. Acesso comercial | B10: 0: sem canal elegível (descartar); 1: canal geral; 2: canal comercial claro e caminho ao responsável. | C10: Instagram como único canal não entra na prospecção.
A11: CAPACIDADE ESTIMADA · 5 critérios | B11: Sinais públicos ou respostas da clínica, 0–2 por critério; total 0–10. | C11: Não confirma orçamento disponível. Referência comercial: implantação de R$ 3.490 + R$ 397/mês. Confirme capacidade real em conversa.
A12: 1. Estrutura / unidades | B12: 0: operação individual declarada; 1: uma clínica estruturada; 2: múltiplas unidades publicadas. | C12: Não inferir unidades por fotos ou seguidores.
A13: 2. Equipe publicada | B13: 0: profissional individual declarado; 1: equipe pequena; 2: equipe multiprofissional descrita. | C13: Quantidade só deve ser anotada quando publicada.
... A20: Clínica fora do Brasil | B20: Preencha o país da clínica. A última coluna destaca automaticamente FORA DO BRASIL. | C20: Localização internacional não elimina a clínica se o proprietário brasileiro estiver confirmado.

Sheet Mapa do segmento
A1: SEGMENTO | B1: Necessidades a investigar | C1: Oferta pertinente | D1: Questões de qualificação
A2: Clínicas de estética facial | B2: Apresentação de tratamentos, solicitação de horários, aprovação, conteúdo atualizado. | C2: Site, perfil do cliente, solicitações e painel de conteúdo. | D2: Como recebem pedidos? Quem confirma? Como atualizam tratamentos e fotos?
A3: Clínicas corporais e integradas | B3: Diversidade de tratamentos e equipe; pedidos por vários canais. | C3: Catálogo organizado, painel e cadastro de clientes. | D3: Quantos profissionais atendem? Onde registram os pedidos?
A4: Institutos e clínicas com várias unidades | B4: Identidade visual, contatos corretos por unidade e responsabilidade pelo conteúdo. | C4: Sites configurados por clínica e painel central, conforme escopo disponível. | D4: Cada unidade tem agenda própria? Quem administra o sistema atual?
A5: Profissionais individuais | B5: Apresentação profissional e facilidade de contato; orçamento pode exigir escopo menor. | C5: Implantação simples e suporte delimitado. | D5: O problema justifica painel completo ou um projeto menor?
A6: Clínicas com sistema já implantado | B6: Integrações e preservação da operação atual. | C6: Avaliar complementar o site; não prometer substituir ou integrar sem análise. | D6: Qual sistema utilizam? Há contrato ou integração disponível?
A7: Antes de vender | B7: Validar cadastro, login, pedido de horário e aprovação em produção. | C7: Demonstração com dados fictícios, escopo, treinamento e contrato. | D7: Quais funções estão prontas? Quem paga infraestrutura e domínio?
A8: Recursos futuros | B8: Lembretes, pagamento, lista de espera e integrações dependem de implementação. | C8: Apresentar como opcionais em evolução, não como entrega pronta. | D8: Há necessidade e orçamento para desenvolver?
A9: Limite desta análise | B9: Mapa comercial elaborado a partir do escopo do projeto; não é levantamento estatístico do setor. | C9: Pesquisa externa bloqueada neste ambiente. | D9: Dados de mercado, concorrentes e novos contatos ainda exigem fontes oficiais acessíveis.
